{"en:teas-and-herbal-teas-and-coffees":{"parents":["en:beverages"],"name":{"en":"Teas and herbal teas and coffees"},"synonyms":{"en":["Teas and herbal teas and coffees"]}},"en:dressings":{"parents":["en:dressings-and-sauces"],"synonyms":{"ja":["ドレッシング"],"en":["Dressings"]},"name":{"en":"Dressings","ja":"ドレッシング"}},"en:artificially-sweetened-beverages":{"parents":["en:beverages"],"name":{"en":"Artificially sweetened beverages"},"synonyms":{"en":["Artificially sweetened beverages"]}},"en:fats":{"children":["en:animal-fats","en:vegetable-margarines","en:vegetable-oils"],"name":{"ja":"油脂","en":"Fats"},"synonyms":{"ja":["油脂"],"en":["Fats"]},"parents":["en:fats-and-sauces"]},"en:poultry":{"parents":["en:meat"],"synonyms":{"nl":["Gevogelte"],"en":["Poultry"]},"name":{"nl":"Gevogelte","en":"Poultry"}},"en:fish-meat-eggs":{"children":["en:eggs","en:fish-and-seafood","en:meat","en:offals","en:processed-meat"],"name":{"en":"Fish‚ Meat‚ Eggs"},"synonyms":{"en":["Fish‚ Meat‚ Eggs"]}},"en:cereals":{"name":{"en":"Cereals","ja":"穀物"},"synonyms":{"en":["Cereals"],"ja":["穀物"]},"parents":["en:cereals-and-potatoes"],"children":["en:other-refined-cereals","en:other-whole-grain-cereals","en:white-pasta","en:white-rice","en:whole-grain-pasta","en:whole-grain-rice"]},"en:fresh-cheese":{"synonyms":{"fr":["Fromage frais ou spécialité laitière fraiche"],"en":["Fresh cheese"]},"name":{"fr":"Fromage frais ou spécialité laitière fraiche","en":"Fresh cheese"}},"en:dehydrated-soups":{"parents":["en:fruits-and-vegetables"],"synonyms":{"es":["Sopas deshidratadas"],"fr":["Soupes déshydratées"],"en":["Dehydrated Soups"],"nl":["Gedroogde soepen"]},"name":{"fr":"Soupes déshydratées","es":"Sopas deshidratadas","en":"Dehydrated Soups","nl":"Gedroogde soepen"}},"en:white-chocolate":{"parents":["en:chocolate-products"],"synonyms":{"ja":["ホワイトチョコレート"],"en":["White chocolate"],"nl":["Witte chocolade"]},"name":{"nl":"Witte chocolade","en":"White chocolate","ja":"ホワイトチョコレート"}},"en:fruit-nectars":{"synonyms":{"en":["Fruit nectars"]},"name":{"en":"Fruit nectars"},"parents":["en:beverages"]},"en:blue-cheese":{"parents":["en:cheese"],"synonyms":{"fr":["Fromage persillé"],"en":["Blue cheese"],"ja":["ブルーチーズ"]},"name":{"ja":"ブルーチーズ","en":"Blue cheese","fr":"Fromage persillé"}},"en:vegetables":{"parents":["en:fruits-and-vegetables"],"synonyms":{"ja":["野菜"],"en":["Vegetables"],"nl":["Groenten"]},"name":{"ja":"野菜","en":"Vegetables","nl":"Groenten"}},"en:dressings-and-sauces":{"name":{"en":"Dressings and sauces"},"synonyms":{"en":["Dressings and sauces"]},"parents":["en:fats-and-sauces"],"children":["en:dressings","en:sauces"]},"en:whole-grain-soft-bread":{"parents":["en:bread"],"synonyms":{"en":["Whole grain soft bread"]},"name":{"en":"Whole grain soft bread"}},"en:bread":{"parents":["en:cereals-and-potatoes"],"synonyms":{"nl":["Brood"],"en":["Bread"],"ja":["パン"]},"name":{"nl":"Brood","en":"Bread","ja":"パン"},"children":["en:white-bread","en:white-soft-bread","en:whole-grain-bread","en:whole-grain-soft-bread"]},"en:appetizers":{"parents":["en:salty-snacks"],"synonyms":{"ja":["前菜"],"en":["Appetizers"]},"name":{"en":"Appetizers","ja":"前菜"}},"en:fish-and-seafood":{"children":["en:fatty-fish","en:lean-fish","en:seafood","en:smoked-fish"],"parents":["en:fish-meat-eggs"],"synonyms":{"en":["Fish and seafood"]},"name":{"en":"Fish and seafood"}},"en:fruit-juices":{"parents":["en:beverages"],"synonyms":{"en":["Fruit juices"]},"name":{"en":"Fruit juices"}},"en:meat":{"children":["en:meat-other-than-poultry","en:poultry"],"parents":["en:fish-meat-eggs"],"name":{"ja":"肉","nl":"Vlees","en":"Meat"},"synonyms":{"ja":["肉"],"nl":["Vlees"],"en":["Meat"]}},"en:milk-and-yogurt":{"parents":["en:milk-and-dairy-products"],"name":{"en":"Milk and yogurt"},"synonyms":{"en":["Milk and yogurt"]},"children":["en:plain-milk-and-yogurt","en:sweetened-milk-and-yogurt"]},"en:vegetable-oils":{"name":{"en":"Vegetable oils","ja":"植物油"},"synonyms":{"en":["Vegetable oils"],"ja":["植物油"]},"parents":["en:fats"]},"en:unknown-food-group-2":{"synonyms":{"nl":["Onbekende voedselgroep 2"],"en":["Unknown food group 2"],"es":["Grupo de alimentos desconocido 2"],"fr":["Groupe alimentaire de niveau 2 inconnu"]},"name":{"es":"Grupo de alimentos desconocido 2","fr":"Groupe alimentaire de niveau 2 inconnu","nl":"Onbekende voedselgroep 2","en":"Unknown food group 2"}},"en:biscuits-and-cakes":{"synonyms":{"en":["Biscuits and cakes"]},"name":{"en":"Biscuits and cakes"},"parents":["en:sugary-snacks"]},"en:pizza-pies-and-quiches":{"synonyms":{"en":["Pizza pies and quiches"]},"name":{"en":"Pizza pies and quiches"},"parents":["en:composite-foods"]},"en:sweets":{"parents":["en:sugary-snacks"],"synonyms":{"en":["Sweets"]},"name":{"en":"Sweets"}},"en:white-bread":{"parents":["en:bread"],"synonyms":{"en":["White bread"]},"name":{"en":"White bread"}},"en:dairy-desserts":{"parents":["en:milk-and-dairy-products"],"synonyms":{"en":["Dairy desserts"]},"name":{"en":"Dairy desserts"}},"en:white-rice":{"parents":["en:cereals"],"synonyms":{"nl":["Witte rijst"],"en":["White rice"],"ja":["白米"]},"name":{"ja":"白米","nl":"Witte rijst","en":"White rice"}},"en:milk-chocolate":{"parents":["en:chocolate-products"],"synonyms":{"es":["Chocolate con leche"],"fr":["Chocolat au lait"],"nl":["Melkchocolade"],"en":["Milk chocolate"],"de":["Vollmilchschokolade"],"ja":["ミルクチョコレート"]},"name":{"en":"Milk chocolate","nl":"Melkchocolade","fr":"Chocolat au lait","es":"Chocolate con leche","de":"Vollmilchschokolade","ja":"ミルクチョコレート"}},"en:smoked-fish":{"parents":["en:fish-and-seafood"],"name":{"en":"Smoked fish"},"synonyms":{"en":["Smoked fish"]}},"en:soft-cheese":{"synonyms":{"ja":["ソフトチーズ"],"en":["Soft cheese"],"fr":["Fromage à pâte molle"]},"name":{"en":"Soft cheese","ja":"ソフトチーズ","fr":"Fromage à pâte molle"},"parents":["en:cheese"]},"en:fruits-and-vegetables":{"children":["en:dehydrated-soups","en:dried-fruits","en:fresh-soups","en:fruits","en:soups","en:vegetables"],"synonyms":{"en":["Fruits and vegetables"],"nl":["Groenten en fruit"],"ja":["果物と野菜"],"fr":["Fruits et légumes"],"es":["Frutas y verduras"]},"name":{"en":"Fruits and vegetables","nl":"Groenten en fruit","ja":"果物と野菜","es":"Frutas y verduras","fr":"Fruits et légumes"}},"en:meat-other-than-poultry":{"parents":["en:meat"],"name":{"en":"Meat other than poultry"},"synonyms":{"en":["Meat other than poultry"]}},"en:white-pasta":{"synonyms":{"nl":["Witte pasta"],"en":["White pasta"]},"name":{"en":"White pasta","nl":"Witte pasta"},"parents":["en:cereals"]},"en:animal-fats":{"name":{"en":"Animal fats","ja":"動物性油脂"},"synonyms":{"ja":["動物性油脂"],"en":["Animal fats"]},"parents":["en:fats"]},"en:whole-grain-rice":{"name":{"en":"Whole grain rice"},"synonyms":{"en":["Whole grain rice"]},"parents":["en:cereals"]},"en:other-whole-grain-cereals":{"name":{"en":"Other whole grain cereals"},"synonyms":{"en":["Other whole grain cereals"]},"parents":["en:cereals"]},"en:vegetable-margarines":{"parents":["en:fats"],"synonyms":{"en":["Vegetable margarines"]},"name":{"en":"Vegetable margarines"}},"en:fruits":{"parents":["en:fruits-and-vegetables"],"name":{"nl":"Fruit","en":"Fruits","ja":"果物"},"synonyms":{"ja":["果物"],"nl":["Fruit"],"en":["Fruits"]}},"en:breakfast-cereals":{"parents":["en:cereals-and-potatoes"],"name":{"en":"Breakfast cereals","nl":"Ontbijtgranen"},"synonyms":{"en":["Breakfast cereals"],"nl":["Ontbijtgranen"]}},"en:beverages":{"children":["en:artificially-sweetened-beverages","en:fruit-juices","en:fruit-nectars","en:plant-based-milk-substitutes","en:sweetened-beverages","en:teas-and-herbal-teas-and-coffees","en:unsweetened-beverages","en:waters-and-flavored-waters"],"name":{"ja":"飲料","en":"Beverages"},"synonyms":{"ja":["飲料"],"en":["Beverages"]}},"en:salty-and-fatty-products":{"parents":["en:salty-snacks"],"name":{"en":"Salty and fatty products"},"synonyms":{"en":["Salty and fatty products"]}},"en:unknown-food-group-3":{"name":{"nl":"Onbekende voedselgroep 3","en":"Unknown food group 3","fr":"Groupe alimentaire de niveau 3 inconnu","es":"Grupo de alimentos desconocido 3"},"synonyms":{"en":["Unknown food group 3"],"nl":["Onbekende voedselgroep 3"],"es":["Grupo de alimentos desconocido 3"],"fr":["Groupe alimentaire de niveau 3 inconnu"]}},"en:soups":{"name":{"fr":"Soupes","es":"Sopas","nl":"Soepen","en":"Soups","ja":"スープ"},"synonyms":{"fr":["Soupes"],"es":["Sopas"],"ja":["スープ"],"en":["Soups"],"nl":["Soepen"]},"parents":["en:fruits-and-vegetables"]},"en:eggs":{"synonyms":{"nl":["Eieren"],"en":["Eggs"],"ja":["卵"]},"name":{"ja":"卵","nl":"Eieren","en":"Eggs"},"parents":["en:fish-meat-eggs"]},"en:sweetened-milk-and-yogurt":{"synonyms":{"en":["Sweetened milk and yogurt"]},"name":{"en":"Sweetened milk and yogurt"},"parents":["en:milk-and-yogurt"]},"en:processed-cheese":{"name":{"fr":"Fromage fondu","en":"Processed cheese"},"synonyms":{"fr":["Fromage fondu"],"en":["Processed cheese"]}},"en:pastries":{"parents":["en:sugary-snacks"],"synonyms":{"en":["Pastries"]},"name":{"en":"Pastries"}},"en:nut-butter":{"name":{"ja":"ナッツバター","en":"Nut butter"},"synonyms":{"ja":["ナッツバター"],"en":["Nut butter"]},"parents":["en:nuts"]},"en:ice-cream":{"parents":["en:milk-and-dairy-products"],"synonyms":{"ja":["アイスクリーム"],"nl":["Ijs","ijsjes"],"en":["Ice cream"]},"name":{"ja":"アイスクリーム","en":"Ice cream","nl":"Ijs"}},"en:other-refined-cereals":{"parents":["en:cereals"],"synonyms":{"en":["Other refined cereals"]},"name":{"en":"Other refined cereals"}},"en:sugary-snacks":{"children":["en:biscuits-and-cakes","en:chocolate-products","en:pastries","en:sweets"],"name":{"en":"Sugary snacks"},"synonyms":{"en":["Sugary snacks"]}},"en:fresh-soups":{"name":{"nl":"Verse soepen","en":"Fresh soups"},"synonyms":{"nl":["Verse soepen"],"en":["Fresh soups"]},"parents":["en:fruits-and-vegetables"]},"en:legumes":{"synonyms":{"en":["Legumes"]},"name":{"en":"Legumes"},"parents":["en:cereals-and-potatoes"]},"en:whole-grain-bread":{"parents":["en:bread"],"synonyms":{"en":["Whole grain bread"]},"name":{"en":"Whole grain bread"}},"en:sweetened-beverages":{"parents":["en:beverages"],"name":{"ja":"甘味料入り飲料","en":"Sweetened beverages","nl":"Gezoete dranken"},"synonyms":{"ja":["甘味料入り飲料"],"en":["Sweetened beverages"],"nl":["Gezoete dranken"]}},"en:waters-and-flavored-waters":{"synonyms":{"nl":["Water en gearomatiseerd water"],"en":["Waters and flavored waters"],"ja":["水とフレーバードウォーター"]},"name":{"en":"Waters and flavored waters","nl":"Water en gearomatiseerd water","ja":"水とフレーバードウォーター"},"parents":["en:beverages"]},"en:hard-cheese":{"name":{"ja":"ハードチーズ","en":"Hard cheese","fr":"Fromage à pâte pressée cuite"},"synonyms":{"fr":["Fromage à pâte pressée cuite"],"ja":["ハードチーズ"],"en":["Hard cheese"]},"parents":["en:cheese"]},"en:alcoholic-beverages":{"synonyms":{"ja":["酒","さけ"],"en":["Alcoholic beverages"]},"name":{"ja":"酒","en":"Alcoholic beverages"}},"en:offals":{"parents":["en:fish-meat-eggs"],"name":{"ja":"もつ","en":"Offals"},"synonyms":{"en":["Offals"],"ja":["もつ"]}},"en:processed-meat":{"synonyms":{"en":["Processed meat"],"ja":["加工肉"]},"name":{"en":"Processed meat","ja":"加工肉"},"parents":["en:fish-meat-eggs"]},"en:milk-and-dairy-products":{"children":["en:cheese","en:dairy-desserts","en:ice-cream","en:milk-and-yogurt"],"name":{"en":"Milk and dairy products"},"synonyms":{"en":["Milk and dairy products"]}},"en:cheese":{"children":["en:blue-cheese","en:hard-cheese","en:soft-cheese"],"synonyms":{"en":["Cheese"],"nl":["Kaas"],"ja":["チーズ"]},"name":{"nl":"Kaas","en":"Cheese","ja":"チーズ"},"parents":["en:milk-and-dairy-products"]},"en:lean-fish":{"name":{"en":"Lean fish"},"synonyms":{"en":["Lean fish"]},"parents":["en:fish-and-seafood"]},"en:salted-nuts":{"name":{"nl":"Gezouten noten","en":"Salted nuts"},"synonyms":{"en":["Salted nuts"],"nl":["Gezouten noten"]},"parents":["en:nuts"]},"en:unknown-food-group-1":{"name":{"fr":"Groupe alimentaire de niveau 1 inconnu","es":"Grupo de alimentos desconocido 1","nl":"Onbekende voedselgroep 1","en":"Unknown food group 1"},"synonyms":{"nl":["Onbekende voedselgroep 1"],"en":["Unknown food group 1"],"fr":["Groupe alimentaire de niveau 1 inconnu"],"es":["Grupo de alimentos desconocido 1"]}},"en:dark-chocolate":{"name":{"en":"Dark chocolate","nl":"Pure chocolade","ja":"ダークチョコレート"},"synonyms":{"ja":["ダークチョコレート"],"en":["Dark chocolate"],"nl":["Pure chocolade"]},"parents":["en:chocolate-products"]},"en:potatoes":{"parents":["en:cereals-and-potatoes"],"name":{"ja":"芋","nl":"Aardappelen","en":"Potatoes"},"synonyms":{"ja":["芋"],"nl":["Aardappelen"],"en":["Potatoes"]}},"en:composite-foods":{"children":["en:one-dish-meals","en:pizza-pies-and-quiches","en:sandwiches"],"name":{"en":"Composite foods"},"synonyms":{"en":["Composite foods"]}},"en:chocolate-products":{"children":["en:dark-chocolate","en:milk-chocolate","en:other-chocolate-based-products","en:white-chocolate"],"synonyms":{"nl":["Chocoladeproducten"],"en":["Chocolate products"],"ja":["チョコレート製品"]},"name":{"ja":"チョコレート製品","nl":"Chocoladeproducten","en":"Chocolate products"},"parents":["en:sugary-snacks"]},"en:salty-snacks":{"name":{"de":"Salzige Snacks","en":"Salty snacks","nl":"Zoute snacks","es":"Snacks salados","fr":"Snacks salés"},"synonyms":{"es":["Snacks salados"],"fr":["Snacks salés"],"de":["Salzige Snacks"],"en":["Salty snacks"],"nl":["Zoute snacks"]},"children":["en:appetizers","en:nuts","en:salty-and-fatty-products"]},"en:other-chocolate-based-products":{"parents":["en:chocolate-products"],"name":{"en":"Other chocolate-based products"},"synonyms":{"en":["Other chocolate-based products"]}},"en:plain-milk-and-yogurt":{"synonyms":{"en":["Plain milk and yogurt"]},"name":{"en":"Plain milk and yogurt"},"parents":["en:milk-and-yogurt"]},"en:sandwiches":{"parents":["en:composite-foods"],"name":{"en":"Sandwiches","ja":"サンドイッチ"},"synonyms":{"ja":["サンドイッチ"],"en":["Sandwiches"]}},"en:plant-based-milk-substitutes":{"synonyms":{"en":["Plant-based milk substitutes"]},"name":{"en":"Plant-based milk substitutes"},"parents":["en:beverages"]},"en:sauces":{"name":{"en":"Sauces","ja":"ソース"},"synonyms":{"ja":["ソース"],"en":["Sauces"]},"parents":["en:dressings-and-sauces"]},"en:one-dish-meals":{"synonyms":{"en":["One-dish meals"]},"name":{"en":"One-dish meals"},"parents":["en:composite-foods"]},"en:unsalted-nuts":{"synonyms":{"nl":["Ongezouten noten"],"en":["Unsalted nuts"]},"name":{"en":"Unsalted nuts","nl":"Ongezouten noten"},"parents":["en:nuts"]},"en:cereals-and-potatoes":{"children":["en:bread","en:breakfast-cereals","en:cereals","en:legumes","en:potatoes"],"name":{"ja":"穀物とじゃがいも","nl":"Granen en aardappelen","en":"Cereals and potatoes"},"synonyms":{"en":["Cereals and potatoes"],"nl":["Granen en aardappelen"],"ja":["穀物とじゃがいも"]}},"en:dried-fruits":{"name":{"fr":"Fruits secs","es":"Frutas secas","nl":"Gedroogde vruchten","en":"Dried fruits"},"synonyms":{"en":["Dried fruits"],"nl":["Gedroogde vruchten","gedroogd fruit"],"fr":["Fruits secs"],"es":["Frutas secas"]},"parents":["en:fruits-and-vegetables"]},"en:seafood":{"synonyms":{"en":["Seafood"]},"name":{"en":"Seafood"},"parents":["en:fish-and-seafood"]},"en:white-soft-bread":{"name":{"en":"White soft bread"},"synonyms":{"en":["White soft bread"]},"parents":["en:bread"]},"en:nuts":{"children":["en:nut-butter","en:salted-nuts","en:unsalted-nuts"],"parents":["en:salty-snacks"],"name":{"ja":"ナッツ","nl":"Noten","en":"Nuts"},"synonyms":{"en":["Nuts"],"nl":["Noten"],"ja":["ナッツ"]}},"en:fatty-fish":{"parents":["en:fish-and-seafood"],"synonyms":{"en":["Fatty fish"]},"name":{"en":"Fatty fish"}},"en:whole-grain-pasta":{"parents":["en:cereals"],"synonyms":{"en":["Whole grain pasta"]},"name":{"en":"Whole grain pasta"}},"en:unsweetened-beverages":{"parents":["en:beverages"],"name":{"en":"Unsweetened beverages"},"synonyms":{"en":["Unsweetened beverages"]}},"en:fats-and-sauces":{"synonyms":{"en":["Fats and sauces"]},"name":{"en":"Fats and sauces"},"children":["en:dressings-and-sauces","en:fats"]}}