{"en:folate":{"children":["en:calcium-l-methylfolate","en:folic-acid"],"name":{"et":"Folaat","de":"Folat","hu":"Folát","pt":"Folato","nl":"Folaat","lv":"Folāts","en":"Folate","pl":"Folian","lt":"Foliatai","sk":"Folát","sl":"Folat","sv":"Folat","mt":"Folat","es":"Folato","ro":"Folat","fi":"Folaatti","cs":"Folát","it":"Folato","bg":"Фолат"},"synonyms":{"hu":["Folát"],"pt":["Folato"],"en":["Folate"],"nl":["Folaat"],"lv":["Folāts"],"et":["Folaat"],"de":["Folat"],"fi":["Folaatti"],"cs":["Folát"],"es":["Folato"],"ro":["Folat"],"it":["Folato"],"bg":["Фолат"],"sk":["Folát"],"pl":["Folian"],"lt":["Foliatai"],"mt":["Folat"],"sv":["Folat"],"sl":["Folat"]}},"en:phylloquinone":{"wikipedia":{"en":"https://en.wikipedia.org/wiki/Phytomenadione"},"parents":["en:vitamin-k"],"name":{"bg":"Филохинон","or":"ଫାଇଟୋମେନାଡିଓନ","fa":"فیلوکینون","cs":"Fyllochinon","fi":"Fyllokinoni","ro":"Filochinonă","es":"Filoquinona","mt":"Fillokinona","sv":"Fyllokinon","sl":"Filokinon","hr":"Vitamin K1","lt":"Filochinonas","pl":"Filochinon","en":"Phylloquinone","nl":"Fyllochinon","hu":"Fillokinon","sh":"Filohinon","et":"Füllokinoon","ar":"فايتوميناديون","ca":"Filloquinona","el":"Φυλλοκινόνη","vi":"Phytomenadione","it":"Fillochinone","fr":"Phylloquinone","ja":"フィロキノン","ky":"Филлохинон","sr":"Filohinon","sk":"Fylochinón","xx":"K1","da":"Fyllokinon","zh":"叶绿基甲萘醌","lv":"Filohinons","pt":"Filoquinona","ko":"필로퀴논","de":"Phyllochinon","ru":"Филлохинон"},"synonyms":{"hr":["vitamin K1"],"pl":["filochinon","fitomenadion","witamina K1"],"lt":["filochinonas","fitomenadionas"],"mt":["fillokinona","fitomenadjona"],"sl":["filokinon","fitomenadion"],"sv":["fyllokinon","fytomenadion"],"fi":["fyllokinoni","fytomenadioni","K1-vitamiini"],"cs":["fyllochinon","fytomenadion","Vitamin K1"],"fa":["فیلوکینون"],"es":["filoquinona","fitomenadiona","vitamina K1"],"ro":["filochinonă","fitomenadionă"],"bg":["Филохинон","фитоменадион"],"or":["ଫାଇଟୋମେନାଡିଓନ"],"et":["füllokinoon","fütomenadioon"],"ar":["فايتوميناديون"],"sh":["Filohinon"],"hu":["fillokinon","fitomenadion","K1-vitamin"],"nl":["fyllochinon","fytomenadion","Vitamine K1"],"en":["phylloquinone","phytomenadione","Vitamin K1"],"sk":["fylochinón","fytomenadion","Vitamín K1"],"xx":["K1"],"ky":["Филлохинон"],"ja":["フィロキノン","ビタミンK1","ビタミンＫ１","ビタミン K1","ビタミン Ｋ１","V.K1","Ｖ．Ｋ１","V.K₁","V-K1","ＶーＫ１","V-K₁"],"sr":["Filohinon"],"fr":["phylloquinone","phytoménadione","phytonadione","Vitamine K1","K1"],"it":["fillochinone","fitomenadione","vitamina K1"],"vi":["Phytomenadione"],"ca":["filloquinona","Vitamina K1"],"el":["φυλλοκινόνη","φυτομεναδιόνη"],"ru":["Филлохинон"],"de":["Phyllochinon","Phytomenadion","Vitamin K1"],"ko":["필로퀴논"],"da":["Fyllokinon"],"pt":["filoquinona","fitomenadiona"],"zh":["叶绿基甲萘醌"],"lv":["filohinons","fitomenadions"]},"wikidata":{"en":"Q186093"}},"en:d-pantothenate-sodium":{"parents":["en:pantothenic-acid"],"name":{"pl":"D-pantotenian sodu","lt":"Natrio D-pantotenatas","sk":"D-pantotenát sodný","sl":"Natrijev D-pantotenat","sv":"Natrium-D-pantotenat","mt":"D-pantotenat sodju","fr":"D-pantothénate de sodium","es":"D-pantotenato sódico","ro":"D-pantotenat de sodiu","fi":"D-pantotenaatti natrium","cs":"D-pantothenát sodný","it":"D-pantotenato sodio","el":"D-παντοθενικό νάτριο","bg":"D-пантотенат натрий","et":"Naatrium-D-pantotenaat","de":"Natrium-D-pantothenat","hu":"Nátrium-D-pantotenát","pt":"D-pantotenato de sódio","nl":"Natrium-D-pantothenaat","en":"D-pantothenate sodium","lv":"Nātrija D-pantotenāts"},"synonyms":{"hu":["nátrium-D-pantotenát"],"pt":["D-pantotenato de sódio"],"lv":["nātrija D-pantotenāts"],"nl":["natrium-D-pantothenaat"],"en":["D-pantothenate sodium"],"et":["naatrium-D-pantotenaat"],"de":["Natrium-D-pantothenat"],"fi":["D-pantotenaatti natrium"],"cs":["D-pantothenát sodný"],"es":["D-pantotenato sódico"],"fr":["D-pantothénate de sodium"],"ro":["D-pantotenat de sodiu"],"it":["D-pantotenato sodio"],"el":["D-παντοθενικό νάτριο"],"bg":["D-пантотенат натрий"],"sk":["D-pantotenát sodný"],"pl":["D-pantotenian sodu"],"lt":["natrio D-pantotenatas"],"mt":["D-pantotenat sodju"],"sl":["natrijev D-pantotenat"],"sv":["natrium-D-pantotenat"]}},"en:vitamin-k":{"synonyms":{"et":["K-vitamiin"],"hu":["K-vitamin"],"pt":["Vitamina K"],"nl":["Vitamine K"],"lv":["K vitamīns"],"en":["Vitamin K"],"pl":["Witamina K"],"lt":["Vitaminas K"],"sk":["Vitamín K"],"ja":["ビタミンK","ビタミンＫ","ビタミン K","ビタミン Ｋ","V.K","Ｖ．Ｋ","V-K","ＶーＫ"],"mt":["Vitamina K"],"fr":["Vitamine K"],"es":["Vitamina K"],"ro":["Vitamina K"],"fi":["K-vitamiini"],"it":["Vitamina K"],"bg":["Витамин K"],"el":["Βιταμίνη K"]},"name":{"sk":"Vitamín K","pl":"Witamina K","lt":"Vitaminas K","mt":"Vitamina K","ja":"ビタミンK","fi":"K-vitamiini","es":"Vitamina K","fr":"Vitamine K","ro":"Vitamina K","it":"Vitamina K","el":"Βιταμίνη K","bg":"Витамин K","et":"K-vitamiin","hu":"K-vitamin","pt":"Vitamina K","en":"Vitamin K","nl":"Vitamine K","lv":"K vitamīns"},"children":["en:menaquinone","en:phylloquinone","en:vitamin-k3"]},"fi:vitamiini-a-ja-d2":{"parents":["en:ergocalciferol","en:vitamin-a"],"synonyms":{"fi":["Vitamiini A- ja D2"]},"name":{"fi":"Vitamiini A- ja D2"}},"en:folacin":{"name":{"fr":"Folacine","es":"Folacina","nl":"Folacin","en":"Folacin"},"synonyms":{"en":["folacin"],"nl":["folacin"],"es":["folacina"],"fr":["Folacine"]},"parents":["en:folic-acid"]},"en:beta-carotene":{"wikipedia":{"en":"https://en.wikipedia.org/wiki/Beta-Carotene"},"name":{"zh":"Β-胡萝卜素","lv":"Beta-karotīns","ko":"베타카로틴","th":"บีตา-แคโรทีน","ru":"Бета-каротин","it":"Beta-carotene","sr":"Бета-каротен","ta":"பீட்டா கரோட்டீன்","sk":"Betakarotén","mk":"Бета-каротен","id":"Beta-karoten","eu":"Beta-karoteno","bg":"Бета каротин","mn":"Бета каротин","es":"Beta-caroteno","fa":"بتاکاروتن","fi":"Beetakaroteeni","sv":"Betakaroten","sl":"Beta karoten","mt":"Beta-karotên","lt":"B-karotenas","gl":"Beta-caroteno","hr":"Beta-karoten","pt":"Betacaroteno","da":"Betakaroten","is":"Beta-karótín","de":"Beta-Carotin","el":"Β-καροτένιο","nn":"Betakaroten","ca":"Beta-carotè","vi":"Beta-Carotene","fr":"Bêtacarotène","he":"בטא-קרוטן","ja":"Β-カロテン","hi":"बीटा कैरोटीन","nl":"Beta-caroteen","en":"Beta-carotene","ms":"Beta-Karotena","hu":"Béta-karotin","sh":"Beta-karoten","et":"Beetakaroteen","ro":"Beta-caroten","cs":"Beta-karoten","pl":"Beta-karoten"},"synonyms":{"ja":["β-カロテン"],"hi":["बीटा कैरोटीन"],"vi":["Beta-Carotene"],"el":["β-καροτένιο"],"nn":["betakaroten"],"ca":["beta-carotè","beta-carotens","betacarotè"],"fr":["bêtacarotène","Bêta-carotène","beta-carotène"],"he":["בטא-קרוטן"],"de":["Beta-Carotin"],"is":["Beta-karótín"],"pt":["Betacaroteno","beta-caroteno"],"da":["Betakaroten"],"pl":["beta-karoten"],"ro":["Beta-caroten"],"cs":["beta-karoten","β-karoten"],"sh":["Beta-karoten"],"et":["Beetakaroteen"],"ms":["Beta-Karotena"],"nl":["Beta-caroteen","bèta-caroteen"],"en":["beta-carotene"],"hu":["Béta-karotin"],"sr":["бета-каротен"],"ta":["பீட்டா கரோட்டீன்"],"sk":["Betakarotén","beta-karotén"],"it":["beta-carotene"],"th":["บีตา-แคโรทีน"],"ru":["бета-каротин","β-каротин"],"lv":["Beta-karotīns"],"zh":["Β-胡萝卜素"],"ko":["베타카로틴"],"sl":["Beta karoten","beta-karoten"],"sv":["Betakaroten"],"mt":["Beta-karotên","beta-karotina"],"gl":["Beta-caroteno"],"lt":["b-karotenas","Beta karotenas"],"hr":["beta-karoten"],"bg":["Бета каротин"],"es":["beta-caroteno"],"mn":["Бета каротин"],"fi":["beetakaroteeni","betakaroteeni"],"fa":["بتاکاروتن"],"eu":["Beta-karoteno"],"mk":["Бета-каротен"],"id":["Beta-karoten"]},"parents":["en:vitamin-a"],"wikidata":{"en":"Q306135"},"children":["en:beta-carotene-dye","en:provitamin-a"]},"en:d-alpha-tocopheryl-acetate":{"name":{"hu":"D-alfa-tokoferil-acetát","en":"D-alpha tocopheryl acetate","nl":"D-alfa-tocoferylacetaat","lv":"D-alfa-tokoferilacetāts","pt":"Acetato de D-alfa-tocoferilo","et":"D-alfa-tokoferüülatsetaat","de":"D-alpha-Tocopherylacetat","ro":"Acetat de tocoferil D-alfa","fr":"Acétate de D-alpha-tocophérol","es":"Acetato de D-alfa tocoferilo","cs":"D- α-tokoferyl-acetát","fi":"D-alfa-tokoferyyliasetaatti","el":"Οξική D-α-τοκοφερόλη","bg":"D-алфатокоферил ацетат","it":"Acetato di D-alfa-tocoferile","lt":"D-alfa-tokoferilacetatas","pl":"Octan D-alfa-tokoferylu","sk":"D-alfa-tokoferylacetát","sv":"D-alfa-tokoferylacetat","sl":"D-alfa-tokoferil acetat","mt":"Aċetat ta' D-alfa-tokoferil"},"synonyms":{"sk":["D-alfa-tokoferylacetát"],"pl":["octan D-alfa-tokoferylu"],"lt":["D-alfa-tokoferilacetatas"],"mt":["Aċetat ta' D-alfa-tokoferil"],"sl":["D-alfa-tokoferil acetat"],"sv":["D-alfa-tokoferylacetat"],"fi":["D-alfa-tokoferyyliasetaatti"],"cs":["D- α-tokoferyl-acetát"],"fr":["acétate de D-alpha-tocophérol"],"es":["acetato de D-alfa tocoferilo"],"ro":["acetat de tocoferil D-alfa"],"it":["acetato di D-alfa-tocoferile"],"el":["οξική D-α-τοκοφερόλη"],"bg":["D-алфатокоферил ацетат"],"et":["D-alfa-tokoferüülatsetaat"],"de":["D-alpha-Tocopherylacetat"],"hu":["D-alfa-tokoferil-acetát"],"pt":["acetato de D-alfa-tocoferilo"],"nl":["D-alfa-tocoferylacetaat"],"en":["D-alpha tocopheryl acetate","alpha tocopheryl acetate","alpha tocopherol acetate"],"lv":["D-alfa-tokoferilacetāts"]},"parents":["en:vitamin-e"],"wikidata":{"en":"Q364160"}},"en:calcium-l-ascorbate":{"parents":["en:vitamin-c"],"name":{"it":"L-ascorbato di calcio","bg":"Калциев-L-аскорбат","el":"L-ασκορβικό ασβέστιο","fi":"Kalsium-L-askorbaatti","cs":"L-askorbát vápenatý","fr":"L-ascorbate de calcium","es":"L-ascorbato cálcico","ro":"L-ascorbat de calciu","mt":"L-assorbat tal-kalċju","sv":"Kalcium-L-askorbat","sl":"Kalcijev-L-askorbat","sk":"L-askorban vápenatý","pl":"L-askorbinian wapnia","lt":"Kalcio L-askorbatas","pt":"L-ascorbato de cálcio","nl":"Calcium-L-ascorbaat","en":"Calcium-L-ascorbate","lv":"Kalcija L-askorbāts","hu":"Kalcium-L-aszkorbát","de":"Calcium-L-ascorbat","et":"Kaltsium-L-askorbaat"},"synonyms":{"mt":["L-assorbat tal-kalċju"],"sl":["kalcijev-L-askorbat"],"sv":["kalcium-L-askorbat"],"sk":["L-askorban vápenatý"],"pl":["L-askorbinian wapnia"],"lt":["kalcio L-askorbatas"],"it":["L-ascorbato di calcio"],"bg":["Калциев-L-аскорбат"],"el":["L-ασκορβικό ασβέστιο"],"fi":["kalsium-L-askorbaatti"],"cs":["L-askorbát vápenatý"],"fr":["L-ascorbate de calcium","ascorbate de calcium"],"es":["L-ascorbato cálcico"],"ro":["L-ascorbat de calciu"],"de":["Calcium-L-ascorbat"],"et":["kaltsium-L-askorbaat"],"pt":["L-ascorbato de cálcio"],"en":["calcium-L-ascorbate","calcium ascorbate"],"nl":["calcium-L-ascorbaat"],"lv":["kalcija L-askorbāts"],"hu":["kalcium-L-aszkorbát"]}},"en:cholecalciferol":{"wikipedia":{"en":"https://en.wikipedia.org/wiki/Cholecalciferol"},"vegetarian":{"en":"maybe"},"parents":["en:vitamin-d"],"vegan":{"en":"maybe"},"synonyms":{"fr":["cholécalciférol","Vitamine D3"],"nn":["kolekalciferol","kolekalsiferol","vitamin D3","D3-vitamin"],"el":["χοληκαλσιφερόλη","Βιταμίνη D3"],"ca":["Colecalciferol","vitamina D3","D3"],"vi":["cholecalciferol","vitamin D3"],"eo":["Vitamino D3"],"hi":["कॉलेकैल्सिफेरॉल"],"ja":["ビタミンD3","ビタミンＤ３","ビタミン D3","ビタミン Ｄ３","V.D3","Ｖ．Ｄ３","V.D₃","V-D3","ＶーＤ３","V-D₃"],"yi":["וויטאמין D3"],"ka":["ვიტამინი D3"],"su":["Vitamin D3"],"pt":["colecalciferol","Vitamina D3"],"cy":["colecalcifferol","Fitamin D3"],"de":["Cholecalciferol","Vitamin D3"],"cs":["cholekalciferol","Vitamín D3"],"ro":["colecalciferol","Vitamina D3"],"nb":["vitamin D3","kolekalsiferol"],"sq":["Vitamina D3"],"ug":["ۋىتامىن D3"],"pl":["cholekalcyferol","Witamina D3"],"tr":["Kolekalsiferol","Vitamin D3"],"hu":["D3-vitamin","Kolekalciferol","D3"],"tt":["D3 витамины"],"en":["Cholecalciferol","vitamin D3","D3"],"nl":["Cholecalciferol","vitamine D3"],"ms":["Kolekalsiferol","Vitamin D3"],"et":["kolekaltsiferool"],"sh":["Holekalciferol"],"it":["Colecalciferolo","Vitamina D3"],"sk":["Cholekalciferol"],"sr":["holekalciferol","Vitamin D3"],"ko":["비타민 D3"],"zh":["胆钙化醇","维生素D3"],"uk":["Холекальциферол","Вітамін D3"],"lv":["D3 vitamīns","holekalciferols"],"tg":["Витамини D3"],"af":["Vitamien D3"],"ru":["Холекальциферол","Витамин д3"],"bs":["Holekalciferol","Vitamin D3"],"az":["D3 vitamini"],"fa":["کلکلسیفرول"],"fi":["kolekalsiferoli","D3-vitamiini"],"mn":["Д3 витамин"],"es":["colecalciferol","vitamina D3","D3"],"bg":["Витамин D3","Холекалциферол"],"or":["କୋଲିକ୍ୟାଲସିଫେରଲ"],"hr":["Vitamin D3","kolekalciferol"],"lt":["Vitaminas D3","cholekalciferolis"],"mt":["kolekalċiferol"],"sl":["Holekalciferol"],"sv":["vitamin D3","kolekalciferol"],"oc":["Cholecalciferol","Vitamina D3"],"ar":["كوليكالسيفيرول"]},"name":{"tr":"Kolekalsiferol","pl":"Cholekalcyferol","ug":"ۋىتامىن D3","sq":"Vitamina D3","nb":"Vitamin D3","ro":"Colecalciferol","cs":"Cholekalciferol","sh":"Holekalciferol","et":"Kolekaltsiferool","ms":"Kolekalsiferol","nl":"Cholecalciferol","en":"Cholecalciferol","tt":"D3 витамины","hu":"D3-vitamin","yi":"וויטאמין D3","ja":"ビタミンD3","hi":"कॉलेकैल्सिफेरॉल","eo":"Vitamino D3","vi":"Cholecalciferol","nn":"Kolekalciferol","el":"Χοληκαλσιφερόλη","ca":"Colecalciferol","fr":"Cholécalciférol","de":"Cholecalciferol","cy":"Colecalcifferol","pt":"Colecalciferol","su":"Vitamin D3","ka":"ვიტამინი D3","sl":"Holekalciferol","sv":"Vitamin D3","mt":"Kolekalċiferol","lt":"Vitaminas D3","hr":"Vitamin D3","or":"କୋଲିକ୍ୟାଲସିଫେରଲ","bg":"Витамин D3","es":"Colecalciferol","mn":"Д3 витамин","fi":"Kolekalsiferoli","fa":"کلکلسیفرول","az":"D3 vitamini","ar":"كوليكالسيفيرول","oc":"Cholecalciferol","sr":"Holekalciferol","sk":"Cholekalciferol","it":"Colecalciferolo","bs":"Holekalciferol","ru":"Холекальциферол","af":"Vitamien D3","tg":"Витамини D3","uk":"Холекальциферол","zh":"胆钙化醇","lv":"D3 vitamīns","ko":"비타민 D3"},"wikidata":{"en":"Q139347"}},"en:thiamin-mononitrate":{"parents":["en:thiamin"],"name":{"sk":"Tiamínmononitrát","it":"Mononitrato di tiamina","ca":"Mononitrat de tiamina","el":"Μονονιτρική θειαμίνη","fr":"Mononitrate de thiamine","de":"Thiaminmononitrat","pt":"Mononitrato de tiamina","lv":"Tiamīna mononitrāts","da":"Thiamin-mononitrat","sv":"Tiaminmononitrat","sl":"Tiamin mononitrat","mt":"Mononitrat tat-tijamina","pl":"Monoazotan tiaminy","lt":"Tiamino mononitratas","hr":"Tiamin mononitrat","bg":"Тиамин мононитрат","es":"Mononitrato de tiamina","ro":"Mononitrat de tiamină","fi":"Tiamiinimononitraatti","cs":"Thiamin-mononitrát","et":"Tiamiinmononitraat","nl":"Thiaminemononitraat","en":"Thiamin mononitrate","hu":"Tiamin-mononitrát"},"synonyms":{"sk":["tiamínmononitrát"],"it":["mononitrato di tiamina"],"ca":["mononitrat de tiamina"],"el":["μονονιτρική θειαμίνη"],"fr":["mononitrate de thiamine"],"de":["Thiaminmononitrat"],"da":["thiamin-mononitrat"],"pt":["mononitrato de tiamina"],"lv":["tiamīna mononitrāts"],"mt":["mononitrat tat-tijamina"],"sv":["tiaminmononitrat"],"sl":["tiamin mononitrat"],"hr":["tiamin mononitrat","tiaminmononitrat"],"pl":["monoazotan tiaminy"],"lt":["tiamino mononitratas"],"bg":["Тиамин мононитрат"],"fi":["tiamiinimononitraatti"],"cs":["thiamin-mononitrát"],"es":["mononitrato de tiamina"],"ro":["mononitrat de tiamină"],"et":["tiamiinmononitraat"],"nl":["thiaminemononitraat"],"en":["thiamin mononitrate","thiamine mononitrate"],"hu":["tiamin-mononitrát"]}},"en:retinyl-palmitate":{"wikipedia":{"en":"https://en.wikipedia.org/wiki/Retinyl_palmitate"},"parents":["en:vitamin-a"],"synonyms":{"el":["παλμιτική ρετινόλη"],"nn":["retinylpalmitat"],"it":["palmitato di retinile"],"fr":["palmitate de rétinol"],"sr":["Retinil palmitat"],"sk":["retinylpalmitát"],"lv":["retinilpalmitāts"],"pt":["palmitato de retinilo"],"de":["Retinylpalmitat"],"bg":["Ретинил палмитат"],"fa":["رتینیل پالمیتات"],"cs":["retinyl-palmitát"],"fi":["retinyylipalmitaatti"],"ro":["palmitat de retinil"],"es":["palmitato de retinilo","palmitato"],"mt":["palmitat tar-retinil"],"sv":["retinylpalmitat"],"sl":["retinil palmitat"],"lt":["retinilo palmitatas"],"pl":["palmitynian retinylu"],"nl":["retinylpalmitaat"],"en":["retinyl palmitate","Vitamin A palmitate","palmitate"],"hu":["retinil-palmitát"],"sh":["Retinil palmitat"],"et":["retinüülpalmitaat"]},"name":{"hu":"Retinil-palmitát","nl":"Retinylpalmitaat","en":"Retinyl palmitate","et":"Retinüülpalmitaat","sh":"Retinil palmitat","fi":"Retinyylipalmitaatti","fa":"رتینیل پالمیتات","cs":"Retinyl-palmitát","es":"Palmitato de retinilo","ro":"Palmitat de retinil","bg":"Ретинил палмитат","pl":"Palmitynian retinylu","lt":"Retinilo palmitatas","mt":"Palmitat tar-retinil","sl":"Retinil palmitat","sv":"Retinylpalmitat","pt":"Palmitato de retinilo","lv":"Retinilpalmitāts","de":"Retinylpalmitat","fr":"Palmitate de rétinol","it":"Palmitato di retinile","el":"Παλμιτική ρετινόλη","nn":"Retinylpalmitat","sk":"Retinylpalmitát","sr":"Retinil palmitat"},"wikidata":{"en":"Q7316807"}},"en:biotin":{"children":["en:d-biotin","en:vitamin-b8"],"name":{"fi":"Biotiini","fr":"Biotine","es":"Biotina","ro":"Biotină","it":"Biotina","el":"Βιοτίνη","bg":"Биотин","hr":"Biotin","sk":"Biotín","pl":"Biotyna","lt":"Biotinas","mt":"Bijotina","hu":"Biotin","pt":"Biotina","en":"Biotin","nl":"Biotine","lv":"Biotīns","et":"Biotiin","de":"Biotin"},"synonyms":{"es":["Biotina","Vitamina B7"],"fr":["Biotine","Vitamine B7","Vitamine H"],"ro":["Biotină"],"fi":["Biotiini"],"it":["Biotina"],"bg":["Биотин"],"el":["Βιοτίνη"],"pl":["Biotyna"],"lt":["Biotinas"],"hr":["biotin"],"sk":["Biotín"],"mt":["Bijotina"],"hu":["Biotin","B7-vitamin","H-vitamin"],"pt":["Biotina"],"lv":["Biotīns"],"nl":["Biotine"],"en":["biotin"],"et":["Biotiin"],"de":["Biotin","Vitamin B7"]}},"en:vitamin-a":{"wikidata":{"en":"Q18225"},"children":["da:vitamin-a-og-d","en:beta-carotene","en:retinol","en:retinyl-acetate","en:retinyl-palmitate","fi:vitamiini-a-ja-d2"],"name":{"ja":"ビタミンA","mt":"Vitamina A","sk":"Vitamín A","lt":"Vitaminas A","pl":"Witamina A","bg":"Витамин А","el":"Βιταμίνη A","it":"Vitamina A","he":"ויטמין A","fi":"A-vitamiini","ro":"Vitamina A","es":"Vitamina A","fr":"Vitamine A","de":"Vitamin A","et":"A-vitamiin","zh":"维生素A","nl":"Vitamine A","en":"Vitamin A","lv":"A vitamīns","pt":"Vitamina A","hu":"A-vitamin"},"synonyms":{"es":["Vitamina A"],"fr":["Vitamine A","vitamine Pro-A"],"ro":["Vitamina A"],"fi":["A-vitamiini"],"he":["ויטמין A","רטינול"],"it":["Vitamina A"],"el":["Βιταμίνη A"],"bg":["Витамин А"],"pl":["Witamina A"],"lt":["Vitaminas A"],"sk":["Vitamín A"],"mt":["Vitamina A"],"ja":["ビタミンA","ビタミンＡ","ビタミン A","ビタミン Ａ","V.A","Ｖ．Ａ","V-A","ＶーＡ"],"hu":["A-vitamin"],"pt":["Vitamina A"],"en":["Vitamin A"],"zh":["维生素A"],"nl":["Vitamine A"],"lv":["A vitamīns"],"et":["A-vitamiin"],"de":["Vitamin A"]}},"en:nicotinamide":{"synonyms":{"et":["nikotiinamiid"],"de":["Nicotinamid"],"hu":["nikotinamid"],"lv":["nikotīnamīds"],"nl":["nicotinamide"],"en":["nicotinamide"],"pt":["nicotinamida"],"sk":["nikotínamid"],"lt":["nikotinamidas"],"pl":["nikotynamid","amid kwasu nikotynowego"],"mt":["nikotinamide"],"sl":["nikotinamid"],"sv":["nikotinamid"],"cs":["nikotinamid"],"fi":["nikotiiniamidi"],"ro":["nicotinamidă"],"es":["nicotinamida"],"bg":["Никотинамид"],"el":["νικοτιναμίδιο"]},"name":{"hu":"Nikotinamid","en":"Nicotinamide","nl":"Nicotinamide","lv":"Nikotīnamīds","pt":"Nicotinamida","et":"Nikotiinamiid","de":"Nicotinamid","ro":"Nicotinamidă","es":"Nicotinamida","cs":"Nikotinamid","fi":"Nikotiiniamidi","bg":"Никотинамид","el":"Νικοτιναμίδιο","lt":"Nikotinamidas","pl":"Nikotynamid","sk":"Nikotínamid","sv":"Nikotinamid","sl":"Nikotinamid","mt":"Nikotinamide"},"parents":["en:niacin"]},"en:d-pantothenate-calcium":{"parents":["en:pantothenic-acid"],"name":{"fi":"D-pantotenaatti kalsium","cs":"D-pantothenát vápenatý","es":"D-pantotenato cálcico","ro":"D-pantotenat de calciu","bg":"D-пантотенат калций","hr":"Kalcijev D-pantotenat","pl":"D-pantotenian wapnia","lt":"Kalcio D-pantotenatas","mt":"D-pantotenat kalċju","sl":"Kalcijev D-pantotenat","sv":"Kalcium-D-pantotenat","hu":"Kalcium-D-pantotenát","nl":"Calcium-D-pantothenaat","en":"D-pantothenate calcium","et":"Kaltsium-D-pantotenaat","fr":"D-pantothénate de calcium","it":"D-pantotenato calcio","el":"D-παντοθενικό ασβέστιο","sk":"D-pantotenát vápenatý","ja":"パントテン酸ca","pt":"D-pantotenato de cálcio","lv":"Kalcija D-pantotenāts","de":"Calcium-D-pantothenat"},"synonyms":{"et":["kaltsium-D-pantotenaat"],"nl":["calcium-D-pantothenaat"],"en":["D-pantothenate calcium"],"hu":["kalcium-D-pantotenát"],"sv":["kalcium-D-pantotenat"],"sl":["kalcijev D-pantotenat"],"mt":["D-pantotenat kalċju"],"pl":["D-pantotenian wapnia"],"lt":["kalcio D-pantotenatas"],"hr":["kalcijev D-pantotenat"],"bg":["D-пантотенат калций"],"es":["D-pantotenato cálcico"],"ro":["D-pantotenat de calciu"],"fi":["D-pantotenaatti kalsium"],"cs":["D-pantothenát vápenatý"],"de":["Calcium-D-pantothenat"],"pt":["D-pantotenato de cálcio"],"lv":["kalcija D-pantotenāts"],"ja":["パントテン酸ca","パントテン酸カルシウム"],"sk":["D-pantotenát vápenatý"],"it":["D-pantotenato calcio"],"el":["D-παντοθενικό ασβέστιο"],"fr":["D-pantothénate de calcium","D- calcium pantothénate"]}},"en:pantothenic-acid":{"children":["en:d-pantothenate-calcium","en:d-pantothenate-sodium","en:dexpanthenol"],"synonyms":{"bg":["Пантотенова киселина","Витамин B5"],"es":["Ácido pantoténico"],"ro":["Acid pantotenic"],"fi":["Pantoteenihappo"],"cs":["Kyselina pantothenová"],"sv":["Pantotensyra"],"sl":["Pantotenska kislina"],"mt":["Aċidu Pantoteniku"],"pl":["Kwas pantotenowy"],"lt":["Pantoteno rūgštis"],"hr":["vitamin B5"],"en":["Pantothenic Acid","Vitamin B5"],"nl":["Pantotheenzuur"],"hu":["Panoténsav","B5-vitamin"],"et":["Pantoteenhape"],"it":["Acido pantotenico"],"el":["Παντοθενικό οξύ"],"fr":["Acide pantothénique","Vitamine B5"],"ja":["パントテン酸","ビタミンＢ５","ビタミン B5","ビタミン Ｂ５","V.B5","Ｖ．Ｂ５","V.B₅","V-B5","ＶーＢ５","V-B₅"],"sk":["Kyselina pantoténová"],"pt":["Ácido pantoténico"],"lv":["Pantotēn-skābe"],"da":["Pantotensyre","Pantothensyre"],"de":["Pantothensäure","Pantothenat"]},"name":{"nl":"Pantotheenzuur","en":"Pantothenic Acid","hu":"Panoténsav","et":"Pantoteenhape","bg":"Пантотенова киселина","es":"Ácido pantoténico","ro":"Acid pantotenic","fi":"Pantoteenihappo","cs":"Kyselina pantothenová","sv":"Pantotensyra","sl":"Pantotenska kislina","mt":"Aċidu Pantoteniku","pl":"Kwas pantotenowy","lt":"Pantoteno rūgštis","hr":"Vitamin B5","pt":"Ácido pantoténico","lv":"Pantotēn-skābe","da":"Pantotensyre","de":"Pantothensäure","it":"Acido pantotenico","el":"Παντοθενικό οξύ","fr":"Acide pantothénique","ja":"パントテン酸","sk":"Kyselina pantoténová"}},"en:dexpanthenol":{"parents":["en:pantothenic-acid"],"name":{"hu":"Dexpantenol","nl":"Dexpanthenol","lv":"Dekspantenols","en":"Dexpanthenol","pt":"Dexpantenol","et":"Dekspantenool","fi":"Dekspantenoli","ro":"Dexpantenol","fr":"Dexpanthénol","es":"Dexpantenol","el":"Δεξπανθενόλη","bg":"Декспантенол","it":"Dexpantenolo","sk":"Dexpantenol","lt":"Dekspantenolis","pl":"Dekspantenol","mt":"Dexpantenolu","sl":"Dekspantenol","sv":"Dexpantenol"},"synonyms":{"et":["dekspantenool"],"pt":["dexpantenol"],"lv":["dekspantenols"],"nl":["dexpanthenol"],"en":["dexpanthenol"],"hu":["dexpantenol"],"mt":["dexpantenolu"],"sl":["dekspantenol"],"sv":["dexpantenol"],"sk":["dexpantenol"],"pl":["dekspantenol"],"lt":["dekspantenolis"],"it":["dexpantenolo"],"bg":["Декспантенол"],"el":["δεξπανθενόλη"],"fi":["dekspantenoli"],"es":["dexpantenol"],"fr":["dexpanthénol"],"ro":["dexpantenol"]}},"en:d-biotin":{"parents":["en:biotin"],"synonyms":{"hr":["D-biotin"],"hu":["D-biotin"],"en":["D-Biotin"],"nl":["D-biotine"]},"name":{"hu":"D-biotin","hr":"D-biotin","nl":"D-biotine","en":"D-Biotin"}},"en:retinol":{"wikidata":{"en":"Q424976"},"parents":["en:vitamin-a"],"name":{"nl":"Retinol","en":"Retinol","lv":"Retinols","hu":"Retinol","de":"Retinol","et":"Retinool","it":"Retinolo","el":"Ρετινόλη","bg":"Ретинол","fi":"Retinoli","fr":"Rétinol","es":"Retinol","lt":"Retinolis"},"synonyms":{"el":["ρετινόλη"],"bg":["Ретинол"],"it":["retinolo"],"es":["retinol"],"fr":["rétinol"],"fi":["retinoli"],"lt":["retinolis"],"lv":["retinols"],"nl":["retinol"],"en":["retinol"],"hu":["retinol"],"de":["Retinol"],"et":["retinool"]}},"en:thiamin-hydrochloride":{"name":{"de":"Thiaminhydrochlorid","pt":"Cloridrato de tiamina","lv":"Tiamīna hidrohlorīds","sr":"Tiamin-hidrohlorid","sk":"Tiamínhydrochlorid","it":"Cloridrato di tiamina","el":"Υδροχλωρική θειαμίνη","fr":"Chlorhydrate de thiamine","et":"Tiamiinhüdrokloriid","en":"Thiamin hydrochloride","nl":"Thiaminehydrochloride","hu":"Tiamin-hidroklorid","mt":"Idroklorur tat-tijamina","sl":"Tiamin hidroklorid","sv":"Tiaminhydroklorid","hr":"Tiamin-hidroklorid","pl":"Chlorowodorek tiaminy","lt":"Tiamino hidrochloridas","bg":"Тиамин хидрохлорид","fi":"Tiamiinihydrokloridi","cs":"Thiamin-hydrochlorid","es":"Clorhidrato de tiamina","ro":"Clorhidrat de tiamină"},"synonyms":{"sk":["tiamínhydrochlorid"],"sr":["tiamin-hidrohlorid"],"fr":["chlorhydrate de thiamine"],"it":["cloridrato di tiamina"],"el":["υδροχλωρική θειαμίνη"],"de":["Thiaminhydrochlorid"],"pt":["cloridrato de tiamina"],"lv":["tiamīna hidrohlorīds"],"hr":["tiamin-hidroklorid"],"pl":["chlorowodorek tiaminy"],"lt":["tiamino hidrochloridas"],"mt":["idroklorur tat-tijamina"],"sv":["tiaminhydroklorid"],"sl":["tiamin hidroklorid"],"fi":["tiamiinihydrokloridi"],"cs":["thiamin-hydrochlorid"],"es":["clorhidrato de tiamina"],"ro":["clorhidrat de tiamină"],"bg":["Тиамин хидрохлорид"],"et":["tiamiinhüdrokloriid"],"hu":["tiamin-hidroklorid"],"nl":["thiaminehydrochloride"],"en":["thiamin hydrochloride"]},"parents":["en:thiamin"]},"en:d-alpha-tocopheryl-polyethylene-glycol-1000-succinate":{"parents":["en:vitamin-e"],"name":{"sk":"D-alfa –tokoferolpolyetylénglykol-1000 sukcinát","pl":"Bursztynian D-alfa-tokoferolu polietylen glikolu -1000","lt":"D-alfa-tokoferilpolietilenglikol-1000-sukcinatas","mt":"D-alfa-tokoferil polietilene glikol -1000 suċċinat","sv":"D-alfa-tokoferyl-polyetylenglykol 1000 succinat","sl":"D-alfa-tokoferil polietilen glikol-1000 sukcinat","fi":"D-alfa-tokoferyylipolyetyleeniglykoli-1000 sukkinaatti","cs":"Polyethylenglykol 1000","es":"Succinado de D-alfa-tocoferil polietilenglicol-1000","fr":"Succinate de D-alpha-tocophéryl polyéthylène glycol 1000","ro":"Succinat polietilen glicol 1000 de tocoferil D-alfa","it":"Succinato D-alfa-tocoferile polietilenglicole 1000","el":"D-α-τοκοφερυλο-ηλεκτρική πολυαιθυλενο 1000 γλυκόλη","bg":"D-алфа-токоферил полиетилен гликол-1000 сукцинат","et":"D-alfa-tokoferüülpolüeteenglükool-1000-suktsinaat","de":"D-alpha-Tocopheryl-Polyethylenglycol-1000-Succinat","hu":"D-alfa-tokoferil-polietilén-glikol-1000-szukcinát","pt":"Succinato de D-alfa-tocoferil-polietilenoglicol-1000","nl":"D-alfa-tocoferylpolyethyleenglycolsuccinaat 1000","en":"D-alpha-tocopheryl polyethylene glycol-1000 succinate","lv":"D-alfa-tokoferilpolietilēnglikola-1000-sukcināts"},"synonyms":{"lv":["D-alfa-tokoferilpolietilēnglikola-1000-sukcināts","TPGS"],"nl":["D-alfa-tocoferylpolyethyleenglycolsuccinaat 1000","TPGS"],"en":["D-alpha-tocopheryl polyethylene glycol-1000 succinate","TPGS"],"pt":["succinato de D-alfa-tocoferil-polietilenoglicol-1000","TPGS"],"hu":["D-alfa-tokoferil-polietilén-glikol-1000-szukcinát","TPGS"],"de":["D-alpha-Tocopheryl-Polyethylenglycol-1000-Succinat","TPGS"],"et":["D-alfa-tokoferüülpolüeteenglükool-1000-suktsinaat","TPGS"],"el":["D-α-τοκοφερυλο-ηλεκτρική πολυαιθυλενο 1000 γλυκόλη","TPGS"],"bg":["D-алфа-токоферил полиетилен гликол-1000 сукцинат","TPGS"],"it":["succinato D-alfa-tocoferile polietilenglicole 1000","TPGS"],"cs":["polyethylenglykol 1000","ether s -α-tokoferolem","sukcinát","TPGS"],"fi":["D-alfa-tokoferyylipolyetyleeniglykoli-1000 sukkinaatti"],"ro":["succinat polietilen glicol 1000 de tocoferil D-alfa","TPGS"],"fr":["succinate de D-alpha-tocophéryl polyéthylène glycol 1000","TPGS"],"es":["Succinado de D-alfa-tocoferil polietilenglicol-1000","TPGS"],"mt":["D-alfa-tokoferil polietilene glikol -1000 suċċinat","TPGS"],"sl":["D-alfa-tokoferil polietilen glikol-1000 sukcinat","TPGS"],"sv":["D-alfa-tokoferyl-polyetylenglykol 1000 succinat","TPGS"],"sk":["D-alfa –tokoferolpolyetylénglykol-1000 sukcinát","TPGS"],"lt":["D-alfa-tokoferilpolietilenglikol-1000-sukcinatas","TPGS"],"pl":["bursztynian D-alfa-tokoferolu polietylen glikolu -1000","TPGS"]}},"en:nicotinic-acid":{"name":{"et":"Nikotiinhape","de":"Nicotinsäure","hu":"Nikotinsav","nl":"Nicotinezuur","en":"Nicotinic acid","lv":"Nikotīnskābe","pt":"Ácido nicotínico","lt":"Nikotino rūgštis","pl":"Kwas nikotynowy","sk":"Kyselina nikotínová","sv":"Nikotinsyra","sl":"Nikotinska kislina","mt":"Aċidu nikotoniku","ro":"Acid nicotinic","es":"Ácido nicotínico","fr":"Acide nicotinique","cs":"Kyselina nikotinová","fi":"Nikotiinihappo","bg":"Никотинова киселина","el":"Νικοτινικό οξύ","it":"Acido nicotinico"},"synonyms":{"nl":["nicotinezuur"],"en":["nicotinic acid"],"lv":["nikotīnskābe"],"pt":["ácido nicotínico"],"hu":["nikotinsav"],"de":["Nicotinsäure"],"et":["nikotiinhape"],"el":["νικοτινικό οξύ"],"bg":["Никотинова киселина"],"it":["acido nicotinico"],"ro":["acid nicotinic"],"es":["ácido nicotínico"],"fr":["acide nicotinique"],"cs":["kyselina nikotinová"],"fi":["nikotiinihappo"],"sv":["nikotinsyra"],"sl":["nikotinska kislina"],"mt":["aċidu nikotoniku"],"lt":["nikotino rūgštis"],"pl":["kwas nikotynowy"],"sk":["kyselina nikotínová"]},"parents":["en:niacin"]},"en:vitamin-c":{"wikidata":{"en":"Q199678"},"children":["en:calcium-l-ascorbate","en:l-ascorbic-acid","en:l-ascorbyl-6-palmitate","en:potassium-l-ascorbate","en:sodium-l-ascorbate"],"wikipedia":{"en":"https://en.wikipedia.org/wiki/Vitamin_C"},"synonyms":{"he":["ויטמין C"],"fr":["vitamine C","antioxydant e300"],"vi":["Vitamin C"],"el":["Βιταμίνη C"],"ca":["vitamina C"],"eo":["Vitamino C"],"hi":["विटामिन सी"],"ky":["Витамин С"],"ja":["ビタミンC","ビタミンＣ","ビタミン C","ビタミン Ｃ","V.C","Ｖ．Ｃ","V-C","ＶーＣ"],"yi":["וויטאמין C"],"tl":["Bitamina C"],"bn":["ভিটামিন সি"],"ka":["vitamine c"],"da":["C-vitamin"],"hy":["Վիտամին C"],"pt":["vitamina C"],"rw":["Vitamini C"],"su":["Vitamin C"],"cy":["Fitamin C"],"de":["Vitamin C"],"is":["C-vítamín"],"cs":["vitamín C"],"ro":["Vitamina C"],"nb":["Vitamin C"],"sq":["Vitamina C"],"ug":["ۋىتامىن C"],"pl":["witamina C"],"tr":["C vitamini"],"hu":["C-vitamin"],"ms":["Vitamin C"],"nl":["Vitamine C"],"en":["Vitamin C"],"et":["C-vitamiin"],"sh":["Vitamin C"],"it":["vitamina C"],"te":["విటమిన్ సి"],"ta":["உயிர்ச்சத்து சி"],"jv":["Vitamin C"],"sr":["витамин Ц"],"ur":["حیاتین ج"],"ml":["ജീവകം സി"],"ko":["비타민 C"],"zh":["维生素C","维生素 C"],"dv":["ވިޓަމިން ސީ"],"uk":["Вітамін C"],"lv":["C vitamīns"],"ru":["витамин c"],"af":["Vitamien C"],"sw":["Vitamini C"],"bs":["Vitamin C"],"th":["วิตามินซี"],"fi":["C-vitamiini"],"fa":["ویتامین ث"],"az":["C vitamini"],"es":["vitamina C"],"kn":["C ಜೀವ ಸತ್ವ"],"bg":["Витамин C"],"or":["ଜୀବସାର ଗ"],"hr":["vitamin C"],"pa":["ਵਿਟਾਮਿਨ ਸੀ"],"gl":["Vitamina C"],"lt":["Vitaminas C"],"sl":["Vitamin C"],"mr":["क-जीवनसत्त्व"],"id":["Vitamin C"],"mk":["Витамин Ц"],"oc":["Vitamina C"],"eu":["C bitamina"],"ne":["भिटामिन सी"]},"name":{"hi":"विटामिन सी","ky":"Витамин С","ja":"ビタミンC","tl":"Bitamina C","yi":"וויטאמין C","bn":"ভিটামিন সি","he":"ויטמין C","fr":"Vitamine C","vi":"Vitamin C","el":"Βιταμίνη C","ca":"Vitamina C","eo":"Vitamino C","cy":"Fitamin C","de":"Vitamin C","is":"C-vítamín","ka":"Vitamine c","hy":"Վիտամին C","da":"C-vitamin","pt":"Vitamina C","rw":"Vitamini C","su":"Vitamin C","ug":"ۋىتامىن C","pl":"Witamina C","tr":"C vitamini","cs":"Vitamín C","ro":"Vitamina C","nb":"Vitamin C","sq":"Vitamina C","et":"C-vitamiin","sh":"Vitamin C","hu":"C-vitamin","ms":"Vitamin C","nl":"Vitamine C","en":"Vitamin C","ta":"உயிர்ச்சத்து சி","jv":"Vitamin C","sr":"Витамин Ц","it":"Vitamina C","te":"విటమిన్ సి","ru":"Витамин c","af":"Vitamien C","sw":"Vitamini C","bs":"Vitamin C","th":"วิตามินซี","ur":"حیاتین ج","ml":"ജീവകം സി","ko":"비타민 C","uk":"Вітамін C","zh":"维生素C","lv":"C vitamīns","dv":"ވިޓަމިން ސީ","hr":"Vitamin C","pa":"ਵਿਟਾਮਿਨ ਸੀ","gl":"Vitamina C","lt":"Vitaminas C","sl":"Vitamin C","fi":"C-vitamiini","fa":"ویتامین ث","az":"C vitamini","kn":"C ಜೀವ ಸತ್ವ","es":"Vitamina C","bg":"Витамин C","or":"ଜୀବସାର ଗ","oc":"Vitamina C","eu":"C bitamina","ne":"भिटामिन सी","mr":"क-जीवनसत्त्व","id":"Vitamin C","mk":"Витамин Ц"}},"en:d-alpha-tocopherol":{"synonyms":{"et":["D-alfa-tokoferool"],"de":["D-alpha-Tocopherol"],"hu":["D-alfa tokoferol"],"nl":["D-alfa-tocoferol"],"lv":["D-alfa-tokoferols"],"en":["D-alpha tocopherol"],"pt":["D-alfa-tocoferol"],"lt":["D-alfa-tokoferolis"],"pl":["D-alfa tokoferol"],"sk":["D-alfa-tokoferol"],"sl":["D-alfa tokoferol"],"sv":["D-alfa-tokoferol"],"mt":["D-alfa tokoferol"],"ro":["tocoferol D-alfa"],"fr":["D-alpha-tocophérol"],"es":["D-alfa tocoferol"],"cs":["D-α-tokoferol"],"fi":["D-alfa-tokoferoli"],"el":["D-α-τοκοφερόλη"],"bg":["D-алфа токоферол"],"it":["D-alfa-tocoferolo"]},"name":{"hu":"D-alfa tokoferol","pt":"D-alfa-tocoferol","lv":"D-alfa-tokoferols","nl":"D-alfa-tocoferol","en":"D-alpha tocopherol","et":"D-alfa-tokoferool","de":"D-alpha-Tocopherol","fi":"D-alfa-tokoferoli","cs":"D-α-tokoferol","es":"D-alfa tocoferol","fr":"D-alpha-tocophérol","ro":"Tocoferol D-alfa","it":"D-alfa-tocoferolo","el":"D-α-τοκοφερόλη","bg":"D-алфа токоферол","sk":"D-alfa-tokoferol","pl":"D-alfa tokoferol","lt":"D-alfa-tokoferolis","mt":"D-alfa tokoferol","sv":"D-alfa-tokoferol","sl":"D-alfa tokoferol"},"parents":["en:vitamin-e"],"wikidata":{"en":"Q158348"}},"en:calcium-l-methylfolate":{"parents":["en:folate"],"name":{"et":"Kaltsium-L-metüülfolaat","de":"Calcium-L-methylfolat","hu":"Kalcium-L-metil-folát","en":"Calcium-L-methylfolate","nl":"Calcium-L-methylfolaat","lv":"Kalcija-L-metilfolāts","pt":"L-metilfolato de cálcio","sk":"L- metylfolát vápenatý","lt":"Kalcio-L-metilfoliatas","pl":"L-metylfolian wapnia","mt":"L-methylfolate tal-kalċju","sl":"Kalcijev-L-metilfolat","sv":"Kalcium-L-metylfolat","cs":"L-metylfolát vápenatý","fi":"Kalsium-L-metyylifolaatti","ro":"L-metilfolat de calciu","es":"L-metilfolato cálcico","fr":"L-méthylfolate de calcium","el":"L-μεθυλοφολικό ασβέστιο","bg":"Калциев L-метилфолат","it":"L-metilfolato di calcio"},"synonyms":{"hu":["kalcium-L-metil-folát"],"pt":["L-metilfolato de cálcio"],"nl":["calcium-L-methylfolaat"],"lv":["kalcija-L-metilfolāts"],"en":["calcium-L-methylfolate"],"et":["kaltsium-L-metüülfolaat"],"de":["Calcium-L-methylfolat"],"fi":["kalsium-L-metyylifolaatti"],"cs":["L-metylfolát vápenatý"],"fr":["L-méthylfolate de calcium"],"es":["L-metilfolato cálcico"],"ro":["L-metilfolat de calciu"],"it":["L-metilfolato di calcio"],"el":["L-μεθυλοφολικό ασβέστιο"],"bg":["Калциев L-метилфолат"],"sk":["L- metylfolát vápenatý"],"pl":["L-metylfolian wapnia"],"lt":["kalcio-L-metilfoliatas"],"mt":["L-methylfolate tal-kalċju"],"sv":["kalcium-L-metylfolat"],"sl":["kalcijev-L-metilfolat"]}},"en:pyridoxine-dipalmitate":{"parents":["en:vitamin-b6"],"synonyms":{"es":["dipalmitato de piridixona"],"fr":["dipalmitate de pyridoxine"],"ro":["dipalmitat de piridoxină"],"fi":["pyridoksiinidipalmitaatti"],"cs":["pyridoxin-dipalmitát"],"it":["dipalmitato di piridossina"],"bg":["Пиридоксин дипалмитат"],"el":["διπαλμιτική πυριδοξίνη"],"pl":["dwupalmitynian pirydoksyny"],"lt":["piridoksino dipalmitatas"],"sk":["pyridoxíndipalmitát"],"sv":["pyridoxindipalmitat"],"sl":["piridoksin dipalmitat"],"mt":["dipalmitat tal-piridossina"],"hu":["piridoxin-dipalmitát"],"pt":["dipalmitato de piridoxina"],"en":["pyridoxine dipalmitate"],"nl":["pyridoxinedipalmitaat"],"lv":["piridoksīna dipalmitāts"],"et":["püridoksiindipalmitaat"],"de":["Pyridoxindipalmitat"]},"name":{"nl":"Pyridoxinedipalmitaat","lv":"Piridoksīna dipalmitāts","en":"Pyridoxine dipalmitate","pt":"Dipalmitato de piridoxina","hu":"Piridoxin-dipalmitát","de":"Pyridoxindipalmitat","et":"Püridoksiindipalmitaat","bg":"Пиридоксин дипалмитат","el":"Διπαλμιτική πυριδοξίνη","it":"Dipalmitato di piridossina","ro":"Dipalmitat de piridoxină","es":"Dipalmitato de piridixona","fr":"Dipalmitate de pyridoxine","cs":"Pyridoxin-dipalmitát","fi":"Pyridoksiinidipalmitaatti","sl":"Piridoksin dipalmitat","sv":"Pyridoxindipalmitat","mt":"Dipalmitat tal-piridossina","lt":"Piridoksino dipalmitatas","pl":"Dwupalmitynian pirydoksyny","sk":"Pyridoxíndipalmitát"}},"en:pyridoxine-5-phosphate":{"synonyms":{"hu":["pirodoxál-5-foszfát"],"nl":["pyridoxine-5'-fosfaat"],"en":["pyridoxine 5'-phosphate"]},"name":{"hu":"Pirodoxál-5-foszfát","en":"Pyridoxine 5'-phosphate","nl":"Pyridoxine-5'-fosfaat"},"parents":["en:vitamin-b6"]},"en:l-ascorbyl-6-palmitate":{"parents":["en:vitamin-c"],"synonyms":{"ro":["L-ascorbil 6-palmitat"],"fr":["L-ascorbyle 6-palmitate"],"es":["almitato de L-ascorbilo"],"cs":["L-askorbyl-6-palmitát"],"fi":["L-askorbyyli-6-palmitaatti"],"el":["αλμιτικό L-ασκορβύλιο"],"bg":["L-аскорбил 6-палмитат"],"it":["almitato di L-ascorbile"],"lt":["L-askorbil- 6-palmitatas"],"pl":["almitynian-L-askorbylu"],"sk":["L-askorbyl-6-palmitát"],"sl":["L-askorbil 6-palmitat"],"sv":["L-askorbyl-6-palmitat"],"mt":["L-assorbil 6-palmitat"],"hu":["L-aszkorbil-6-palmitát"],"nl":["almityl-L-ascorbinezuur"],"en":["L-ascorbyl 6-palmitate"],"lv":["L-askorbil-6-palmitāts"],"pt":["almitato de L-ascorbilo"],"et":["L-askorbüül-6-palmitaat"],"de":["L-Ascorbyl-6-palmitat"]},"name":{"es":"Almitato de L-ascorbilo","fr":"L-ascorbyle 6-palmitate","ro":"L-ascorbil 6-palmitat","fi":"L-askorbyyli-6-palmitaatti","cs":"L-askorbyl-6-palmitát","it":"Almitato di L-ascorbile","el":"Αλμιτικό L-ασκορβύλιο","bg":"L-аскорбил 6-палмитат","pl":"Almitynian-L-askorbylu","lt":"L-askorbil- 6-palmitatas","sk":"L-askorbyl-6-palmitát","sv":"L-askorbyl-6-palmitat","sl":"L-askorbil 6-palmitat","mt":"L-assorbil 6-palmitat","hu":"L-aszkorbil-6-palmitát","pt":"Almitato de L-ascorbilo","nl":"Almityl-L-ascorbinezuur","lv":"L-askorbil-6-palmitāts","en":"L-ascorbyl 6-palmitate","et":"L-askorbüül-6-palmitaat","de":"L-Ascorbyl-6-palmitat"}},"en:vitamin-b12":{"children":["en:cyanocobalamin","en:hydroxocobalamin"],"wikipedia":{"en":"https://en.wikipedia.org/wiki/Vitamin_B12"},"synonyms":{"vi":["Vitamin B12"],"el":["Βιταμίνη B12"],"nn":["kobalamin","B12-vitamin","vitamin B12"],"ca":["cobalamina","vitamina B12","B12"],"eo":["Kobalamino","Vitamino B12"],"he":["ויטמין B12"],"fr":["Cobalamine","vitamine b12","b12"],"ky":["Витамин В12"],"ja":["シアノコバラミン","ビタミンB12","ビタミンＢ１２","ビタミン B12","ビタミン Ｂ１２","V.B12","Ｖ．Ｂ１２","V.B₁₂","V-B12","ＶーＢ１２","V-B₁₂"],"bn":["সায়ানোকোবালেমিন"],"hi":["विटामिन बी१२"],"da":["Vitamin B12"],"hy":["Վիտամին B12"],"pt":["Cobalamina","vitamina B12"],"rw":["Vitamini B12"],"de":["Cobalamine","Vitamin B12","vitamine B12"],"is":["B12-vítamín"],"cy":["cobalamin","Fitamin B12"],"nb":["Kobalamin","Vitamin B12"],"cs":["kobalamin","vitamín B12"],"ro":["Cobalamină","Vitamina B12"],"tr":["B12 vitamini","Vitamin B12"],"pl":["Kobalamina","witamina B12"],"ms":["Vitamin B12"],"nl":["Cobalamine","vitamine B12"],"en":["vitamin b12","cobalamin"],"hu":["B12-vitamin","Kobalamin","B12"],"sh":["Vitamin B12"],"et":["B12-vitamiin","Vitamiin B12"],"lb":["Cobalamin","Vitamin B12"],"it":["Cobalamina","vitamina B12"],"te":["విటమిన్ బీ12"],"ta":["உயிர்ச்சத்து பி12"],"jv":["Vitamin b12"],"sr":["kobalamin","vitamin B12"],"sk":["Kobalamín","Vitamín B12"],"lv":["B12 vitamīns"],"zh":["维生素B12"],"uk":["Кобаламін"],"dv":["ވިޓަމިން ބީ12"],"ko":["비타민 B12"],"th":["วิตามินบี12"],"ru":["витамин B12"],"af":["Vitamien B12"],"bs":["Vitamin B12"],"bg":["витамин В12","кобаламин"],"fi":["Kobalamiini","B12-vitamiini","Vitamiini B12"],"fa":["ویتامین ب۱۲"],"az":["B12 vitamini"],"es":["cobalamina","vitamina B12","B12"],"mn":["Витамин В12"],"mt":["Vitamina B12"],"sv":["Kobalamin","vitamin B12","B12"],"sl":["Vitamin B12"],"hr":["Kobalamin","Vitamin B12","B12","cianokobalamin","cijano-kobalamin"],"lt":["Kobalaminas","Vitaminas B12"],"id":["Vitamin B12"],"kk":["Кобаламин"],"mk":["Кобаламин"],"eu":["Kobalamina","B12 bitamina"],"ne":["भिटामिन बी-१२"],"oc":["Cobalamina","Vitamina B12"],"ar":["فيتامين بي 12"]},"name":{"sh":"Vitamin B12","et":"B12-vitamiin","ms":"Vitamin B12","nl":"Cobalamine","en":"Vitamin b12","hu":"B12-vitamin","tr":"B12 vitamini","pl":"Kobalamina","nb":"Kobalamin","cs":"Kobalamin","ro":"Cobalamină","de":"Cobalamine","is":"B12-vítamín","cy":"Cobalamin","da":"Vitamin B12","hy":"Վիտամին B12","rw":"Vitamini B12","pt":"Cobalamina","ky":"Витамин В12","ja":"シアノコバラミン","bn":"সায়ানোকোবালেমিন","hi":"विटामिन बी१२","vi":"Vitamin B12","ca":"Cobalamina","nn":"Kobalamin","el":"Βιταμίνη B12","eo":"Kobalamino","he":"ויטמין B12","fr":"Cobalamine","eu":"Kobalamina","ne":"भिटामिन बी-१२","oc":"Cobalamina","ar":"فيتامين بي 12","id":"Vitamin B12","kk":"Кобаламин","mk":"Кобаламин","mt":"Vitamina B12","sv":"Kobalamin","sl":"Vitamin B12","hr":"Kobalamin","lt":"Kobalaminas","bg":"Витамин В12","fi":"Kobalamiini","az":"B12 vitamini","fa":"ویتامین ب۱۲","es":"Cobalamina","mn":"Витамин В12","th":"วิตามินบี12","ru":"Витамин B12","af":"Vitamien B12","bs":"Vitamin B12","zh":"维生素B12","uk":"Кобаламін","lv":"B12 vitamīns","dv":"ވިޓަމިން ބީ12","ko":"비타민 B12","ta":"உயிர்ச்சத்து பி12","jv":"Vitamin b12","sr":"Kobalamin","sk":"Kobalamín","it":"Cobalamina","lb":"Cobalamin","te":"విటమిన్ బీ12"}},"en:vitamin-e":{"children":["en:d-alpha-tocopherol","en:d-alpha-tocopheryl-acetate","en:d-alpha-tocopheryl-acid-succinate","en:d-alpha-tocopheryl-polyethylene-glycol-1000-succinate","en:dl-alpha-tocopheryl-acetate"],"wikidata":{"en":"Q141180"},"synonyms":{"pt":["Vitamina E"],"hy":["Վիտամին E"],"da":["Vitamin E"],"ka":["ვიტამინი E"],"de":["Vitamin E"],"eo":["Tokoferolo","vitamino E"],"el":["Βιταμίνη E","τοκοφερολεσ"],"nn":["vitamin E","E-vitamin"],"ca":["Tocoferol","vitamina E"],"vi":["Vitamin E"],"fr":["tocophérol","vitamine e","vitamines e"],"he":["E ויטמין"],"ja":["ビタミンE","ビタミンＥ","ビタミン E","ビタミン Ｅ","V.E","Ｖ．Ｅ","V-E","ＶーＥ"],"ky":["Витамин Е"],"hi":["विटामिन ई"],"nl":["Tocoferol","vitamine E"],"en":["Vitamin E","tocopherol"],"hu":["E-vitamin","Tokoferol"],"sh":["Vitamin E"],"et":["Tokoferoolid","E-vitamiin","Vitamiin E"],"nb":["vitamin E"],"ro":["Vitamina E"],"cs":["tokoferol","vitamín E"],"tr":["Tokoferol","E vitamini"],"si":["විටමින් E"],"pl":["Witamina E"],"ug":["ۋىتامىنE"],"zh":["维生素E"],"uk":["Вітамін E"],"dv":["ވިޓަމިން އީ"],"lv":["E vitamīns"],"ko":["비타민 E"],"ml":["ജീവകം ഇ"],"th":["วิตามินอี"],"af":["Vitamien E"],"ru":["токоферол","витамин E"],"te":["vitamin e"],"it":["Vitamina E"],"sr":["vitamin E"],"jv":["Vitamin E"],"ta":["உயிர்ச்சத்து ஈ"],"sk":["Vitamín E"],"mk":["vitamin e"],"kk":["Е дәрумені"],"id":["Vitamin E"],"mr":["इ-जीवनसत्त्व"],"ne":["भिटामिन ई"],"eu":["E bitamina"],"ar":["فيتامين إي"],"oc":["Vitamina E"],"bg":["Токоферол","Витамин Е"],"es":["Vitamina E","tocoferol"],"fa":["ویتامین ای"],"fi":["Tokoferoli","E-vitamiini"],"sv":["Vitamin E"],"sl":["Tokoferol","vitamin E"],"mt":["tokoferol","Vitamina E"],"lt":["Tokoferolis","Vitaminas E"],"gl":["Vitamina E"],"pa":["ਵਿਟਾਮਿਨ ਈ"],"hr":["vitamin E"]},"name":{"id":"Vitamin E","kk":"Е дәрумені","mk":"Vitamin e","mr":"इ-जीवनसत्त्व","eu":"E bitamina","ne":"भिटामिन ई","oc":"Vitamina E","ar":"فيتامين إي","bg":"Токоферол","fi":"Tokoferoli","fa":"ویتامین ای","es":"Vitamina E","mt":"Tokoferol","sl":"Tokoferol","sv":"Vitamin E","hr":"Vitamin E","pa":"ਵਿਟਾਮਿਨ ਈ","gl":"Vitamina E","lt":"Tokoferolis","uk":"Вітамін E","zh":"维生素E","lv":"E vitamīns","dv":"ވިޓަމިން އީ","ml":"ജീവകം ഇ","ko":"비타민 E","th":"วิตามินอี","ru":"Токоферол","af":"Vitamien E","it":"Vitamina E","te":"Vitamin e","ta":"உயிர்ச்சத்து ஈ","jv":"Vitamin E","sr":"Vitamin E","sk":"Vitamín E","en":"Vitamin E","nl":"Tocoferol","hu":"E-vitamin","sh":"Vitamin E","et":"Tokoferoolid","nb":"Vitamin E","cs":"Tokoferol","ro":"Vitamina E","si":"විටමින් E","tr":"Tokoferol","ug":"ۋىتامىنE","pl":"Witamina E","da":"Vitamin E","hy":"Վիտամին E","pt":"Vitamina E","ka":"ვიტამინი E","de":"Vitamin E","vi":"Vitamin E","ca":"Tocoferol","nn":"Vitamin E","el":"Βιταμίνη E","eo":"Tokoferolo","he":"E ויטמין","fr":"Tocophérol","ky":"Витамин Е","ja":"ビタミンE","hi":"विटामिन ई"},"wikipedia":{"en":"https://en.wikipedia.org/wiki/Vitamin_E"}},"en:riboflavin":{"name":{"et":"Riboflaviin","nl":"Riboflavine","en":"Riboflavin","lv":"Riboflavīns","pt":"Riboflavina","hu":"Riboflavin","ja":"リボフラビン","lt":"Riboflavinas","pl":"Ryboflawina","bg":"Рибофлавин","el":"Ριβοφλαβίνη","it":"Riboflavina","fi":"Riboflaviini","ro":"Riboflavină","fr":"Riboflavine","es":"Riboflavina"},"synonyms":{"ja":["リボフラビン","ビタミンB2","ビタミンＢ２","ビタミン B2","ビタミン Ｂ２","V.B2","Ｖ．Ｂ２","V.B₂","V-B2","ＶーＢ２","V-B₂"],"lt":["Riboflavinas"],"pl":["Ryboflawina"],"bg":["Рибофлавин"],"el":["Ριβοφλαβίνη"],"it":["Riboflavina"],"fi":["Riboflaviini"],"ro":["Riboflavină"],"fr":["Riboflavine","Vitamine B2"],"es":["Riboflavina","Vitamina B2"],"et":["Riboflaviin"],"lv":["Riboflavīns"],"nl":["Riboflavine"],"en":["Riboflavin","Vitamin B2"],"pt":["Riboflavina"],"hu":["Riboflavin","B2-vitamin"]}},"en:l-ascorbic-acid":{"parents":["en:vitamin-c"],"name":{"it":"Acido L-Ascorbico","ca":"Àcid ascòrbic","el":"L-ασκορβικό οξύ","fr":"Acide L-ascorbique","ja":"L-アスコルビン酸","sk":"Kyselina L-askorbová","pt":"Ácido L-ascórbico","lv":"L-askorbīnskābe","zh":"抗坏血酸","de":"L-Ascorbinsäure","ru":"Аскорбиновая кислота","bs":"Askorbinska kiselina","bg":"L-аскорбинова киселина","fi":"L-askorbiinihappo","cs":"L-askorbová kyselina","es":"Ácido L-ascórbico","ro":"Acid L-ascorbic","mt":"L-aċidu askorbiku","tr":"Askorbik asit","sl":"L-askorbinska kislina","sv":"L-askorbinsyra","hr":"L-askorbinska kiselina","pl":"Kwas L-askorbinowy","gl":"Ácido ascórbico","lt":"L–askorbo rūgštis","en":"L-ascorbic acid","nl":"L-ascorbinezuur","hu":"L-aszkorbinsav","et":"L-askorbiinhape"},"synonyms":{"lv":["L-askorbīnskābe","askorbīnskābe"],"zh":["抗坏血酸"],"pt":["Ácido L-ascórbico","Ácido ascórbico"],"bs":["Askorbinska kiselina"],"ru":["Аскорбиновая кислота"],"de":["L-Ascorbinsäure","Ascorbinsäure"],"fr":["acide L-ascorbique","acide ascorbique"],"ca":["àcid ascòrbic"],"el":["L-ασκορβικό οξύ","ασκορβικό οξύ"],"it":["acido L-Ascorbico","acido Ascorbico"],"sk":["kyselina L-askorbová","kyselina askorbová"],"ja":["L-アスコルビン酸","アスコルビン酸"],"hu":["L-aszkorbinsav","aszkorbinsav"],"nl":["L-ascorbinezuur","ascorbinezuur"],"en":["L-ascorbic acid","ascorbic acid"],"et":["L-askorbiinhape","askorbiinhape"],"ro":["acid L-ascorbic","acid ascorbic"],"es":["Ácido L-ascórbico","Ácido ascórbico"],"cs":["L-askorbová kyselina","askorbová kyselina"],"fi":["L-askorbiinihappo","askorbiinihappo"],"bg":["L-аскорбинова киселина","аскорбинова киселина"],"lt":["L–askorbo rūgštis","askorbo rūgštis"],"pl":["kwas L-askorbinowy","kwas askorbinowy"],"gl":["Ácido ascórbico"],"hr":["L-askorbinska kiselina","askorbinska kiselina"],"sv":["L-askorbinsyra","askorbinsyra"],"sl":["L-askorbinska kislina","askorbinska kislina"],"tr":["askorbik asit"],"mt":["L-aċidu askorbiku","aċidu askorbiku"]}},"en:vitamin-b6":{"children":["en:pyridoxine-5-phosphate","en:pyridoxine-dipalmitate","en:pyridoxine-hydrochloride"],"name":{"hu":"B6-vitamin","nl":"Vitamine B6","zh":"维生素B6","lv":"B6 vitamīns","en":"Vitamin B6","pt":"Vitamina B6","et":"B6-vitamiin","de":"Vitamin B6","fi":"B6-vitamiini","ro":"Vitamina B6","es":"Vitamina B6","fr":"Vitamine B6","el":"Βιταμίνη B6","bg":"Витамин B6","it":"Vitamina B6","sk":"Vitamín B6","hr":"Vitamin B6","lt":"Vitaminas B6","pl":"Witamina B6","ja":"ビタミンB6","mt":"Vitamina B6"},"synonyms":{"et":["B6-vitamiin"],"de":["Vitamin B6","Pyridoxin"],"hu":["B6-vitamin","piridoxin"],"pt":["Vitamina B6"],"nl":["Vitamine B6"],"zh":["维生素B6"],"lv":["B6 vitamīns"],"en":["Vitamin B6","Pyridoxin"],"pl":["Witamina B6"],"lt":["Vitaminas B6"],"hr":["vitamin B6","B6"],"sk":["Vitamín B6"],"ja":["ビタミンB6","ビタミンＢ６","ビタミン B6","ビタミン Ｂ６","V.B6","Ｖ．Ｂ６","V.B₆","V-B6","ＶーＢ６","V-B₆"],"mt":["Vitamina B6"],"es":["Vitamina B6"],"fr":["Vitamine B6","Pyridoxine"],"ro":["Vitamina B6"],"fi":["B6-vitamiini"],"it":["Vitamina B6","piridoxina"],"bg":["Витамин B6","Пиридоксин"],"el":["Βιταμίνη B6"]}},"en:thiamin":{"name":{"ru":"Тиамин","af":"Tiamien","sw":"Tiamin","bs":"Vitamin B1","th":"ไทอามีน","ml":"തയാമിൻ","ko":"티아민","tg":"Тиамин","zh":"硫胺","uk":"Тіамін","lv":"Tiamīns","dv":"ވިޓަމިން ބީ1","sk":"Tiamín","ta":"தயமின்","sr":"Vitamin B1","wa":"Tiyamene","lb":"Thiamin","it":"Tiamina","oc":"Tiamina","ar":"فيتامين ب1","eu":"Tiamina","ne":"भिटामिन बी-१","be":"Тыямін","id":"Tiamina","mk":"Витамин Б1","hr":"Tiamin","gl":"Tiamina","lt":"Tiaminas","mt":"Tiamina","sl":"Tiamin","fi":"Tiamiini","az":"Tiamin","fa":"ویتامین ب۱","es":"Tiamina","bg":"Тиамин","or":"ଥାୟାମିନ","cy":"Thiamin","de":"Thiamin","is":"Þíamín","da":"Tiamin","hy":"Թիամին","pt":"Tiamina","rw":"Vitamini B1","su":"Tiamin","hi":"विटामिन बी१","ky":"Витамин В1","ja":"チアミン","bn":"থায়ামিন","he":"ויטמין B1","fr":"Thiamine","vi":"Thiamin","nn":"Tiamin","ca":"Tiamina","el":"Θιαμίνη","eo":"Tiamino","et":"Tiamiin","sh":"Tiamin","hu":"Tiamin","ms":"Tiamina","nl":"Thiamine","en":"Thiamin","ga":"Tiaimín","pl":"Tiamina","tr":"Tiyamin","fo":"Thiamin","cs":"Thiamin","ro":"Tiamină","nb":"Tiamin","sq":"Tiamina"},"synonyms":{"tr":["Tiyamin","B1 vitamini"],"pl":["tiamina","witamina B1"],"ga":["Tiaimín"],"sq":["Tiamina","Vitamina B1"],"nb":["Tiamin"],"ro":["Tiamină","Vitamina B1"],"fo":["Thiamin","Vitamin B1"],"cs":["thiamin","vitamin B1"],"sh":["Tiamin","Vitamin B1"],"et":["Tiamiin","Vitamiin B1"],"en":["Thiamin","thiamine","vitamin b1","B1"],"nl":["thiamine","vitamine B1"],"ms":["Tiamina","Vitamin B1"],"hu":["Tiamin","B1-vitamin"],"bn":["থায়ামিন"],"ja":["チアミン","ビタミンB1","ビタミンＢ１","ビタミン B1","ビタミン Ｂ１","V.B1","Ｖ．Ｂ１","V.B₁","V-B1","ＶーＢ１","V-B₁"],"ky":["Витамин В1"],"hi":["विटामिन बी१"],"eo":["Tiamino","Vitamino B1"],"ca":["tiamina","Vitamina B1"],"nn":["tiamin","vitamin B1"],"el":["θιαμίνη","βιταμίνη Β1"],"vi":["Thiamin"],"fr":["thiamine","vitamines b1","Vitamine B1"],"he":["ויטמין B1"],"is":["Þíamín","B1-vítamín"],"de":["Thiamin","Vitamin B1"],"cy":["Thiamin","Fitamin B1"],"su":["Tiamin"],"rw":["Vitamini B1"],"pt":["tiamina","vitamina B1"],"hy":["Թիամին","Վիտամին B1"],"da":["Tiamin","Vitamin B1"],"sl":["Tiamin","vitamin B1"],"mt":["Tiamina"],"lt":["Tiaminas"],"gl":["Tiamina","Vitamina B1"],"hr":["Tiamin","vitamin B1","B1"],"or":["ଥାୟାମିନ","ଜୀବସାର ଖ୧"],"bg":["Тиамин","Витамин B1"],"es":["tiamina","vitamina b1"],"az":["Tiamin","B1 vitamini"],"fa":["ویتامین ب۱"],"fi":["Tiamiini","Tiamiinia","B1-vitamiini"],"ne":["भिटामिन बी-१"],"eu":["Tiamina","B1 bitamina"],"ar":["فيتامين ب1"],"oc":["Tiamina","Vitamina B1"],"mk":["Витамин Б1"],"id":["Tiamina","Vitamin B1"],"be":["Тыямін"],"sr":["vitamin B1"],"ta":["தயமின்"],"sk":["Tiamín","Vitamín B1"],"lb":["Thiamin","Vitamin B1"],"it":["tiamina","vitamina B1"],"wa":["Tiyamene"],"th":["ไทอามีน","วิตามินบี1"],"bs":["Vitamin B1"],"sw":["Tiamin","B1-vitamin"],"af":["Tiamien"],"ru":["тиамин","Витамин B1"],"uk":["Тіамін","Вітамін B1"],"zh":["硫胺","維他命B1"],"dv":["ވިޓަމިން ބީ1"],"lv":["Tiamīns","B1 vitamīns"],"tg":["Тиамин"],"ko":["티아민","바이타민 B1"],"ml":["തയാമിൻ"]},"wikipedia":{"en":"https://en.wikipedia.org/wiki/Thiamine"},"wikidata":{"en":"Q83187"},"children":["en:thiamin-hydrochloride","en:thiamin-mononitrate"]},"en:dl-alpha-tocopheryl-acetate":{"name":{"et":"DL-alfa-tokoferüülatsetaat","hu":"DL-alfa-tokoferil-acetát","nl":"DL-alfa-tocoferylacetaat","en":"DL-alpha tocopheryl acetate","lt":"DL-alfa-tokoferilacetatas","pl":"Octan DL-alfa-tokoferylu","hr":"DL-alfa-tokoferil acetat","sv":"DL-alfa-tokoferylacetat","sl":"DL-alfa-tokoferil acetat","mt":"Aċetat ta' DL-alfa-tokoferil","ro":"Acetat de tocoferil DL-alfa","es":"Acetato de DL-alfa tocoferilo","cs":"DL-α-tokoferyl-acetát","fi":"DL-alfa-tokoferyyliasetaatti","bg":"DL-алфатокоферил ацетат","de":"DL-alpha-Tocopherylacetat","lv":"DL-alfa-tokoferilacetāts","pt":"Acetato de DL-alfa-tocoferilo","sk":"DL-alfa-tokoferylacetát","sr":"DL-a-tokoferil-acetat","fr":"Acétate de DL-alpha-tocophérol","nn":"Dl-α-tokoferylacetat","el":"Οξική DL-α-τοκοφερόλη","it":"Acetato di DL-alfa-tocoferile"},"synonyms":{"de":["DL-alpha-Tocopherylacetat"],"pt":["acetato de DL-alfa-tocoferilo"],"lv":["DL-alfa-tokoferilacetāts"],"sk":["DL-alfa-tokoferylacetát"],"sr":["DL-a-tokoferil-acetat"],"fr":["acétate de DL-alpha-tocophérol","acétate de DL-alpha-tocophéryle"],"it":["acetato di DL-alfa-tocoferile"],"nn":["dl-α-tokoferylacetat"],"el":["οξική DL-α-τοκοφερόλη"],"et":["DL-alfa-tokoferüülatsetaat"],"hu":["DL-alfa-tokoferil-acetát"],"nl":["DL-alfa-tocoferylacetaat"],"en":["DL-alpha tocopheryl acetate","dl-alpha tocopherol acetate"],"hr":["DL-alfa-tokoferil acetat","DL-a-tokoferilacetat","DL-alpha-tokoferil acetat","dl-alfa-tokoferil-acetat","DL-a-tokoferil acetat"],"pl":["octan DL-alfa-tokoferylu"],"lt":["DL-alfa-tokoferilacetatas"],"mt":["Aċetat ta' DL-alfa-tokoferil"],"sv":["DL-alfa-tokoferylacetat"],"sl":["DL-alfa-tokoferil acetat"],"fi":["DL-alfa-tokoferyyliasetaatti"],"cs":["DL-α-tokoferyl-acetát"],"es":["acetato de DL-alfa tocoferilo","acetato de DL-alfa tocoferol"],"ro":["acetat de tocoferil DL-alfa"],"bg":["DL-алфатокоферил ацетат"]},"parents":["en:vitamin-e"],"wikidata":{"en":"Q27292783"}},"en:pyridoxine-hydrochloride":{"parents":["en:vitamin-b6"],"name":{"sl":"Piridoksin hidroklorid","sv":"Pyridoxinhydroklorid","mt":"Idroklorur tal-piridossina","pl":"Chlorowodorek pirydoksyny","lt":"Piridoksino hidrochloridas","hr":"Piridoksin-hidroklorid","bg":"Пиридоксин хидрохлорид","es":"Clorhidrato de piridoxina","ro":"Clorhidrat de piridoxină","fi":"Pyridoksiinihydrokloridi","cs":"Pyridoxin-hydrochlorid","et":"Püridoksiinvesinikkloriid","nl":"Pyridoxinehydrochloride","en":"Pyridoxine hydrochloride","hu":"Piridoxin-hidroklorid","sk":"Pyridoxínhydrochlorid","it":"Cloridrato di piridossina","el":"Υδροχλωρική πυριδοξίνη","fr":"Chlorhydrate de pyridoxine","de":"Pyridoxinhydrochlorid","pt":"Cloridrato de piridoxina","lv":"Piridoksīna hidrohlorīds"},"synonyms":{"sk":["pyridoxínhydrochlorid"],"it":["cloridrato di piridossina"],"el":["υδροχλωρική πυριδοξίνη"],"fr":["chlorhydrate de pyridoxine"],"de":["Pyridoxinhydrochlorid"],"pt":["cloridrato de piridoxina"],"lv":["piridoksīna hidrohlorīds"],"sv":["pyridoxinhydroklorid"],"sl":["piridoksin hidroklorid"],"mt":["idroklorur tal-piridossina"],"pl":["chlorowodorek pirydoksyny"],"lt":["piridoksino hidrochloridas"],"hr":["piridoksin-hidroklorid"],"bg":["Пиридоксин хидрохлорид"],"es":["clorhidrato de piridoxina"],"ro":["clorhidrat de piridoxină"],"fi":["pyridoksiinihydrokloridi"],"cs":["pyridoxin-hydrochlorid"],"et":["püridoksiinvesinikkloriid"],"nl":["pyridoxinehydrochloride"],"en":["pyridoxine hydrochloride"],"hu":["piridoxin-hidroklorid"]}},"da:vitamin-a-og-d":{"synonyms":{"de":["Vitamin A und D"],"sv":["vitamin A och D","vitamin A och vitamin D"],"da":["vitamin A og D"],"ca":["vitamines A i D","A i D"],"nl":["vitamine A en D","A en D"],"fi":["A- ja D-vitamiini"],"fr":["vitamines A et D","A et D"],"es":["vitaminas A y D","A y D"]},"name":{"ca":"Vitamines A i D","da":"Vitamin A og D","nl":"Vitamine A en D","fi":"A- ja D-vitamiini","es":"Vitaminas A y D","fr":"Vitamines A et D","sv":"Vitamin A och D","de":"Vitamin A und D"},"parents":["en:vitamin-a","en:vitamin-d"]},"en:sodium-l-ascorbate":{"parents":["en:vitamin-c"],"name":{"cs":"L-askorbát sodný","fi":"Natrium-L-askorbaatti","ro":"L-ascorbat de sodiu","es":"L-ascorbato sódico","fr":"L-ascorbate de sodium","bg":"Натриев-L-аскорбат","el":"L-ασκορβικό νάτριο","it":"L-ascorbato di sodio","sk":"L-askorban sodný","lt":"Natrio L-askorbatas","pl":"L-askorbinian sodu","mt":"L-assorbat tas-sodju","sv":"Natrium-L-askorbat","sl":"Natrijev-L-askorbat","hu":"Nátrium-L-aszkorbát","lv":"Nātrija L-askorbāts","nl":"Natrium-L-ascorbaat","en":"Sodium-L-ascorbate","pt":"L-ascorbato de sódio","et":"Naatrium-L-askorbaat","de":"Natrium-L-ascorbat"},"synonyms":{"pt":["L-ascorbato de sódio"],"lv":["nātrija L-askorbāts"],"nl":["natrium-L-ascorbaat"],"en":["sodium-L-ascorbate","fscorbate"],"hu":["nátrium-L-aszkorbát"],"de":["Natrium-L-ascorbat"],"et":["naatrium-L-askorbaat"],"it":["L-ascorbato di sodio"],"el":["L-ασκορβικό νάτριο"],"bg":["Натриев-L-аскорбат"],"fi":["natrium-L-askorbaatti"],"cs":["L-askorbát sodný"],"es":["L-ascorbato sódico"],"fr":["L-ascorbate de sodium","ascorbate de sodium"],"ro":["L-ascorbat de sodiu"],"mt":["L-assorbat tas-sodju"],"sv":["natrium-L-askorbat"],"sl":["natrijev-L-askorbat"],"sk":["L-askorban sodný"],"pl":["L-askorbinian sodu"],"lt":["natrio L-askorbatas"]}},"en:vitamin-b8":{"name":{"fi":"B8-vitamiini","es":"Vitamina b8","fr":"Vitamine b8","ca":"Vitamina B8","bg":"Витамин b8","it":"Vitamina b8","pl":"Witamina B8","ja":"ビタミンＢ８","hu":"B8-vitamin","en":"Vitamin b8","nl":"Vitamine b8","de":"Vitamin B8"},"synonyms":{"fi":["B8-vitamiini","B8"],"es":["vitamina b8","B8"],"fr":["vitamine b8","b8"],"bg":["витамин b8","витамин Б8","B8","инозитол"],"ca":["vitamina B8","B8"],"it":["vitamina b8","B8"],"pl":["witamina B8","B8"],"ja":["ビタミンＢ８","ビタミン B8","ビタミン Ｂ８","V.B8","Ｖ．Ｂ８","V.B₈","V-B8","ＶーＢ８","V-B₈"],"hu":["B8-vitamin","B8"],"en":["vitamin b8","B8"],"nl":["vitamine b8","B8"],"de":["Vitamin B8"]},"parents":["en:biotin"]},"en:provitamin-a":{"wikidata":{"en":"Q306135"},"wikipedia":{"en":"https://en.wikipedia.org/wiki/Beta-Carotene"},"parents":["en:beta-carotene"],"synonyms":{"hr":["provitamina A","iz provitamina A"],"de":["Provitamin A"],"hu":["A-provitamin"],"fi":["provitamiini A","A-vitamiinin provitamiini"],"fr":["pro-vitamine A","provitamine A"],"es":["provitamina A"],"ca":["provitamina A"],"it":["provitamina A"],"en":["provitamin A"],"nl":["provitamine A"]},"name":{"de":"Provitamin A","hr":"Provitamina A","it":"Provitamina A","ca":"Provitamina A","nl":"Provitamine A","en":"Provitamin A","fi":"Provitamiini A","hu":"A-provitamin","es":"Provitamina A","fr":"Pro-vitamine A"}},"en:beta-carotene-dye":{"parents":["en:beta-carotene"],"synonyms":{"es":["colorante de beta-caroteno"],"fr":["colorant bêta-carotène"],"hu":["béta-karotin színezék"],"nl":["bètacaroteenkleurstof"],"en":["beta-carotene dye"],"ca":["colorant de beta-carotè"],"de":["Farbstoff Beta-Carotin"]},"name":{"de":"Farbstoff Beta-Carotin","hu":"Béta-karotin színezék","fr":"Colorant bêta-carotène","es":"Colorante de beta-caroteno","ca":"Colorant de beta-carotè","nl":"Bètacaroteenkleurstof","en":"Beta-carotene dye"}},"en:d-alpha-tocopheryl-acid-succinate":{"synonyms":{"ro":["succinat acid de tocoferil D-alfa"],"fr":["succinate acide de D-alpha-tocophérol"],"es":["Succinato ácido de D-alfa tocoferilo"],"cs":["D-α-tokoferyl-sukcinát"],"fi":["D-alfa-tokoferyylihapon sukkinaatti"],"bg":["D-алфа-токоферил кисел сукцинат"],"el":["όξινη ηλεκτρική D-α-τοκοφερόλη"],"it":["succinato acido di D-alfa-tocoferile"],"lt":["D-alfa-tokoferilo rūgšties sukcinatas"],"pl":["bursztynian D-alfa-tokoferylu"],"sk":["jantáran kyseliny D-alfa-tokoferolovej"],"sv":["D-alfa-tokoferylvätesuccinat"],"sl":["D-alfa-tokoferil kisli sukcinat"],"mt":["Suċċinat aċidu ta' D-alfa-tokoferil"],"hu":["D-alfa-tokoferil-szukcinát"],"en":["D-alpha-tocopheryl acid succinate"],"nl":["D-alfa-tocoferylwaterstof-succinaat"],"lv":["skābais D-alfa-tokoferilsukcināts"],"pt":["succinato ácido de D-alfa-tocoferilo"],"et":["D-alfa-tokoferüülhappe suktsinaat"],"de":["D-alpha-Tocopherylsäuresuccinat"]},"name":{"mt":"Suċċinat aċidu ta' D-alfa-tokoferil","sl":"D-alfa-tokoferil kisli sukcinat","sv":"D-alfa-tokoferylvätesuccinat","sk":"Jantáran kyseliny D-alfa-tokoferolovej","pl":"Bursztynian D-alfa-tokoferylu","lt":"D-alfa-tokoferilo rūgšties sukcinatas","it":"Succinato acido di D-alfa-tocoferile","el":"Όξινη ηλεκτρική D-α-τοκοφερόλη","bg":"D-алфа-токоферил кисел сукцинат","fi":"D-alfa-tokoferyylihapon sukkinaatti","cs":"D-α-tokoferyl-sukcinát","es":"Succinato ácido de D-alfa tocoferilo","fr":"Succinate acide de D-alpha-tocophérol","ro":"Succinat acid de tocoferil D-alfa","de":"D-alpha-Tocopherylsäuresuccinat","et":"D-alfa-tokoferüülhappe suktsinaat","pt":"Succinato ácido de D-alfa-tocoferilo","nl":"D-alfa-tocoferylwaterstof-succinaat","lv":"Skābais D-alfa-tokoferilsukcināts","en":"D-alpha-tocopheryl acid succinate","hu":"D-alfa-tokoferil-szukcinát"},"parents":["en:vitamin-e"]},"en:retinyl-acetate":{"wikidata":{"en":"Q7316808"},"wikipedia":{"en":"https://en.wikipedia.org/wiki/Retinyl_acetate"},"parents":["en:vitamin-a"],"name":{"pl":"Octan retinylu","lt":"Retinilo acetatas","mt":"Aċetat tar-retinil","sl":"Retinil acetat","sv":"Retinylacetat","fi":"Retinyyliasetaatti","cs":"Retinyl-acetát","fa":"استات رتینیل","es":"Acetato de retinilo","ro":"Acetat de retinil","bg":"Ретинил ацетат","et":"Retinüülatsetaatff","sh":"Retinil acetat","hu":"Retinil-acetát","nl":"Retinylacetaat","en":"Retinyl acetate","sk":"Retinylacetát","sr":"Retinil acetat","fr":"Acétate de rétinol","it":"Acetato di retinile","el":"Οξική ρετινόλη","ca":"Acetat de retinol","de":"Retinylacetat","pt":"Acetato de retinilo","lv":"Retinilacetāts"},"synonyms":{"sk":["retinylacetát"],"sr":["Retinil acetat","retinil-acetat"],"fr":["acétate de rétinol"],"it":["acetato di retinile"],"ca":["acetat de retinol"],"el":["οξική ρετινόλη"],"de":["Retinylacetat"],"pt":["acetato de retinilo"],"lv":["retinilacetāts"],"pl":["octan retinylu"],"lt":["retinilo acetatas"],"sl":["retinil acetat"],"sv":["retinylacetat"],"mt":["aċetat tar-retinil"],"es":["acetato de retinilo","acetato de vitamina A"],"ro":["acetat de retinil"],"fi":["retinyyliasetaatti"],"fa":["استات رتینیل"],"cs":["retinyl-acetát"],"bg":["Ретинил ацетат"],"et":["retinüülatsetaatff"],"sh":["Retinil acetat"],"hu":["retinil-acetát"],"nl":["retinylacetaat"],"en":["retinyl acetate","retinol acetate","vitamin A acetate"]}},"en:ergocalciferol":{"name":{"it":"Ergocalciferolo","ca":"Ergocalciferol","nn":"Ergokalsiferol","el":"Εργοκαλσιφερόλη","eo":"Ergokalciferolo","fr":"Ergocalciférol","ja":"エルゴカルシフェロール","sr":"Ергокалциферол","sk":"Ergokalciferol","hi":"एर्गोकैल्सिफेरॉल","pt":"Ergocalciferol","uk":"Ергокальциферол","zh":"麦角钙化醇","lv":"Ergokalciferols","de":"Ergocalciferol","ru":"Эргокальциферол","cy":"Ergocalcifferol","nb":"Ergokalsiferol","bg":"Ергокалциферол","or":"ଏର୍ଗୋକ୍ୟାଲସିଫେରଲ","fi":"Ergokalsiferoli","cs":"Ergokalciferol","fa":"ارگوکالسیفرول","es":"Ergocalciferol","ro":"Ergocalciferol","mt":"Ergokalċiferol","sl":"Ergokalciferol","sv":"Vitamin D2","pl":"Ergokalcyferol","lt":"Ergokalciferolis","en":"Ergocalciferol","nl":"Ergocalciferol","hu":"D2-vitamin","sh":"Ergokalciferol","oc":"Ergocalciferol","et":"Ergokaltsiferool","ar":"إرغوكالسيفيرول"},"synonyms":{"sv":["vitamin D2","D2","ergokalciferol"],"sl":["ergokalciferol"],"mt":["ergokalċiferol"],"lt":["ergokalciferolis"],"pl":["Ergokalcyferol","Witamina D2"],"or":["ଏର୍ଗୋକ୍ୟାଲସିଫେରଲ"],"bg":["Ергокалциферол"],"nb":["ergokalsiferol","Vitamin D2"],"ro":["Ergocalciferol","Vitamina D2"],"es":["ergocalciferol","vitamina D2","D2"],"fa":["ارگوکالسیفرول"],"cs":["ergokalciferol","Vitamín D2"],"fi":["Ergokalsiferoli","D2-vitamiini"],"sh":["Ergokalciferol"],"ar":["إرغوكالسيفيرول"],"et":["ergokaltsiferool"],"oc":["Ergocalciferol"],"nl":["Ergocalciferol","vitamine D2"],"en":["Ergocalciferol","Vitamin D2","D2"],"hu":["D2-vitamin","Ergokalciferol","D2"],"sr":["ергокалциферол"],"ja":["エルゴカルシフェロール","ビタミンD2","ビタミンＤ２","ビタミン D2","ビタミン Ｄ２","V.D2","Ｖ．Ｄ２","V.D₂","V-D2","ＶーＤ２","V-D₂"],"hi":["एर्गोकैल्सिफेरॉल"],"sk":["Ergokalciferol","Vitamín D2"],"eo":["Ergokalciferolo"],"ca":["Ergocalciferol","vitamina D2","D2"],"nn":["ergokalsiferol","vitamin D2"],"el":["εργοκαλσιφερόλη"],"it":["Ergocalciferolo","Vitamina D2"],"fr":["ergocalciférol","vitamine D2"],"de":["Ergocalciferol","Vitamin D2","vitamine D2"],"cy":["ergocalcifferol"],"ru":["эргокальциферол","Витамин D2"],"zh":["麦角钙化醇","维生素D2"],"uk":["Ергокальциферол"],"lv":["ergokalciferols"],"pt":["ergocalciferol"]},"vegan":{"en":"yes"},"parents":["en:vitamin-d"],"vegetarian":{"en":"yes"},"wikipedia":{"en":"https://en.wikipedia.org/wiki/Ergocalciferol"},"children":["fi:vitamiini-a-ja-d2"],"wikidata":{"en":"Q139200"}},"en:vitamin-k3":{"synonyms":{"de":["Vitamin K3"],"pt":["Vitamina K3"],"lv":["K3 vitamīns"],"zh":["维生素K3"],"ja":["ビタミンK3","ビタミンＫ３","ビタミン K3","ビタミン Ｋ３","V.K3","Ｖ．Ｋ３","V.K₃","V-K3","ＶーＫ３","V-K₃"],"sk":["Vitamín K3"],"it":["Vitamina K3"],"el":["Βιταμίνη K3"],"fr":["Vitamine K3","ménadione"],"he":["ויטמין K3","מנדיון"],"et":["Vitamiin K3"],"en":["Vitamin K3"],"nl":["Vitamine K3"],"hu":["K3-vitamin"],"mt":["Vitamina K3"],"pl":["Witamina K3"],"lt":["Vitaminas K3"],"ga":["Vitimín K3"],"bg":["Витамин K3"],"es":["Vitamina K3"],"ro":["Vitamina K3"],"fi":["K3-vitamiini"]},"name":{"de":"Vitamin K3","pt":"Vitamina K3","zh":"维生素K3","lv":"K3 vitamīns","sk":"Vitamín K3","ja":"ビタミンK3","fr":"Vitamine K3","he":"ויטמין K3","it":"Vitamina K3","el":"Βιταμίνη K3","et":"Vitamiin K3","hu":"K3-vitamin","nl":"Vitamine K3","en":"Vitamin K3","pl":"Witamina K3","lt":"Vitaminas K3","ga":"Vitimín K3","mt":"Vitamina K3","es":"Vitamina K3","ro":"Vitamina K3","fi":"K3-vitamiini","bg":"Витамин K3"},"parents":["en:vitamin-k"]},"en:cyanocobalamin":{"name":{"hr":"Cijanokobalamin","lt":"Cianokobalaminas","pl":"Cyjanokobalamina","mt":"Ċjanokobalamina","sv":"Cyanokobalamin","sl":"Cianokobalamin","tr":"Siyanokobalamin","cs":"Kyanokobalamin","fi":"Syanokobalamiini","ro":"Cianocobalamină","es":"Cianocobalamina","bg":"Цианокобаламин","nb":"Cyanocobalamin","et":"Tsüanokobalamiin","oc":"Cianocobalamina","hu":"Cianokobalamin","nl":"Cyanocobalamine","en":"Cyanocobalamin","sk":"Kyanokobalamín","sr":"Цијанокобаламин","fr":"Cyanocobalamine","el":"Κυανοκοβαλαμίνη","it":"Cianocobalamina","lv":"Ciānkobalamīns","pt":"Cianocobalamine"},"synonyms":{"lv":["ciānkobalamīns"],"pt":["cianocobalamine"],"sr":["Цијанокобаламин","cijanokobalamin"],"sk":["kyanokobalamín"],"el":["κυανοκοβαλαμίνη"],"it":["cianocobalamina"],"fr":["cyanocobalamine"],"et":["tsüanokobalamiin"],"oc":["Cianocobalamina"],"nl":["cyanocobalamine"],"en":["cyanocobalamin"],"hu":["cianokobalamin"],"mt":["ċjanokobalamina"],"sl":["cianokobalamin"],"sv":["cyanokobalamin"],"tr":["Siyanokobalamin"],"hr":["cijanokobalamin"],"lt":["cianokobalaminas"],"pl":["cyjanokobalamina"],"bg":["Цианокобаламин"],"nb":["Cyanocobalamin"],"cs":["kyanokobalamin"],"fi":["syanokobalamiini"],"ro":["cianocobalamină"],"es":["cianocobalamina"]},"parents":["en:vitamin-b12"]},"en:folic-acid":{"children":["en:folacin"],"wikidata":{"en":"Q127060"},"wikipedia":{"en":"https://en.wikipedia.org/wiki/Folate"},"parents":["en:folate"],"synonyms":{"cs":["kyselina listová","kyselina pteroylmonoglutamová","vitamín B9"],"ro":["acid folic","acid pteroilmonoglutamic","Vitamina B9"],"nb":["Folsyre"],"sq":["Acidi folik"],"ga":["Aigéad fólach"],"pl":["kwas foliowy","kwas pteroilomonoglutaminowy","Witamina B9","B9/M"],"tr":["Folik asit"],"hu":["folsav","pteroil-monoglutaminsav","B9-vitamin"],"ms":["Asid folik"],"nl":["foliumzuur","pteroylmonoglutaminezuur","Vitamine B9","B9/M"],"en":["folic acid","pteroylmonoglutamic acid","Vitamin B9","B9","vitamin M"],"et":["foolhape","pteroüülmonoglutaamhape"],"sh":["Vitamin B9"],"he":["חומצה פולית"],"fr":["acide folique","acide ptéroylmonoglutamique","Vitamine B9"],"vi":["axit folic"],"ca":["àcid fòlic","vitamina B9","B9","vitamina M"],"nn":["folsyre","vitamin B9"],"el":["φολικό οξύ","πτεροϋλομονογλουταμικό οξύ","Βιταμίνη Β9"],"eo":["foliata acido"],"hi":["फोलिक एसिड"],"ky":["Фоли кычкылы"],"ja":["葉酸","ビタミンB9","ビタミンＢ９","ビタミン B9","ビタミン Ｂ９","V.B9","Ｖ．Ｂ９","V.B₉","V-B9","ＶーＢ９","V-B₉"],"bn":["ফলিক এসিড"],"hy":["Վիտամին B9"],"da":["Folsyre","folinsyre"],"pt":["ácido fólico","ácido pteroilmonoglutâmico","Vitamina B9","B9/M"],"cy":["Asid Ffolig"],"de":["Folsäure","Pteroylmonoglutaminsäure","Vitamin B9"],"is":["Fólínsýra"],"fi":["foolihappo","pteroyylimonoglutamiinihappo","B9-vitamiini","B9","M-vitamiini"],"fa":["اسید فولیک"],"es":["ácido fólico","ácido pteroilmonoglutámico","Vitamina B9","vitamina M"],"bg":["Фолиева киселина","птероилмоноглутаминова киселина","Витамин B9"],"gd":["Searbhag dhuilleagach"],"or":["ଫୋଲିକ ଏସିଡ"],"hr":["folna kiselina","pteroilmonoglutaminska kiselina","pteroylmonoglutamic","vitamin B9","B9"],"gl":["Ácido fólico"],"lt":["folio rūgštis","pteroilmonoglutamo rūgštis"],"mt":["aċidu foliku","aċidu pterojlmonoglutamiku"],"sl":["folna kislina","pteroilmonoglutaminska kislina"],"sv":["folsyra","pteroylmonoglutaminsyra"],"be":["Фоліевая кіслата"],"id":["Asam folat"],"kk":["Птероилглютамин"],"mk":["Фолна киселина"],"oc":["Vitamina B9"],"ar":["حمض الفوليك"],"eu":["Azido foliko"],"lb":["Folsaier"],"it":["acido folico","acido pteroil-monoglutammico","Vitamina B9"],"te":["ఫోలిక్ ఆమ్లం"],"sk":["kyselina listová","kyselina pteroylmonoglutámová"],"ta":["இலைக்காடி"],"sr":["фолна киселина"],"ml":["ഫോളിക് ആസിഡ്"],"ur":["فولک تیزاب"],"ko":["엽산"],"zh":["维生素B9","叶酸"],"uk":["Фолієва кислота"],"dv":["ވިޓަމިން ބީ9"],"lv":["Folijskābe","pteroilmonoglutamīnskābe"],"ru":["фолиевая кислота","Витамин B9","b9"],"bs":["Folna kiselina"],"th":["กรดโฟลิก"]},"name":{"bs":"Folna kiselina","ru":"Фолиевая кислота","th":"กรดโฟลิก","ko":"엽산","ur":"فولک تیزاب","ml":"ഫോളിക് ആസിഡ്","zh":"维生素B9","dv":"ވިޓަމިން ބީ9","uk":"Фолієва кислота","lv":"Folijskābe","sk":"Kyselina listová","sr":"Фолна киселина","ta":"இலைக்காடி","te":"ఫోలిక్ ఆమ్లం","lb":"Folsaier","it":"Acido folico","ar":"حمض الفوليك","oc":"Vitamina B9","eu":"Azido foliko","kk":"Птероилглютамин","mk":"Фолна киселина","be":"Фоліевая кіслата","id":"Asam folat","gl":"Ácido fólico","lt":"Folio rūgštis","hr":"Folna kiselina","sv":"Folsyra","sl":"Folna kislina","mt":"Aċidu foliku","es":"Ácido fólico","fi":"Foolihappo","fa":"اسید فولیک","gd":"Searbhag dhuilleagach","or":"ଫୋଲିକ ଏସିଡ","bg":"Фолиева киселина","cy":"Asid Ffolig","de":"Folsäure","is":"Fólínsýra","pt":"Ácido fólico","hy":"Վիտամին B9","da":"Folsyre","hi":"फोलिक एसिड","bn":"ফলিক এসিড","ky":"Фоли кычкылы","ja":"葉酸","fr":"Acide folique","he":"חומצה פולית","eo":"Foliata acido","vi":"Axit folic","el":"Φολικό οξύ","nn":"Folsyre","ca":"Àcid fòlic","et":"Foolhape","sh":"Vitamin B9","hu":"Folsav","ms":"Asid folik","nl":"Foliumzuur","en":"Folic acid","pl":"Kwas foliowy","ga":"Aigéad fólach","tr":"Folik asit","ro":"Acid folic","cs":"Kyselina listová","sq":"Acidi folik","nb":"Folsyre"}},"en:niacin":{"synonyms":{"lt":["Niacinas"],"pl":["Niacyna","witamina B3","witamina PP"],"sk":["Niacín"],"hr":["niacin","Vitamin B3","nijacin"],"sv":["Niacin"],"ja":["ナイアシン","ビタミンB3","ビタミンＢ３","ビタミン B3","ビタミン Ｂ３","V.B3","Ｖ．Ｂ３","V.B₃","V-B3","ＶーＢ３","V-B₃"],"mt":["Niaċina"],"ro":["Niacină"],"es":["Niacina","Vitamina B3"],"fr":["Niacine","Vitamine B3","Vitamine PP"],"fi":["Niasiini"],"bg":["Ниацин"],"el":["Νιασίνη"],"it":["Niacina"],"nb":["Niacin"],"et":["Niatsiin"],"hu":["Niacin","B3-vitamin","PP-vitamin"],"nl":["Niacine"],"en":["Niacin","Vitamin B3","Vitamin PP"],"lv":["Niacīns"],"pt":["Niacina"]},"name":{"es":"Niacina","fr":"Niacine","ro":"Niacină","fi":"Niasiini","it":"Niacina","nb":"Niacin","bg":"Ниацин","el":"Νιασίνη","pl":"Niacyna","lt":"Niacinas","hr":"Niacin","sk":"Niacín","sv":"Niacin","ja":"ナイアシン","mt":"Niaċina","hu":"Niacin","pt":"Niacina","en":"Niacin","nl":"Niacine","lv":"Niacīns","et":"Niatsiin"},"children":["en:nicotinamide","en:nicotinic-acid"]},"en:hydroxocobalamin":{"parents":["en:vitamin-b12"],"synonyms":{"ro":["hidroxocobalamină"],"es":["hidroxocobalamina"],"fr":["hydroxocobalamine"],"cs":["hydroxokobalamin"],"fi":["hydroksokobalamiini"],"bg":["Хидроксокобаламин"],"el":["υδροξοκοβαλαμίνη"],"it":["idrossocobalamina"],"lt":["hidroksokobalaminas"],"pl":["hydroksokobalamina"],"sk":["hydroxokobalamín"],"sl":["hidroksokobalamin"],"sv":["hydroxykobalamin"],"mt":["idrossokobalamina"],"hu":["hidroxokobalamin"],"en":["hydroxocobalamin"],"nl":["hydroxocobalamine"],"lv":["hidroksokobalamīns"],"pt":["hidroxocobalamine"],"et":["hüdroksokobalamiin"]},"name":{"et":"Hüdroksokobalamiin","hu":"Hidroxokobalamin","pt":"Hidroxocobalamine","lv":"Hidroksokobalamīns","nl":"Hydroxocobalamine","en":"Hydroxocobalamin","pl":"Hydroksokobalamina","lt":"Hidroksokobalaminas","sk":"Hydroxokobalamín","sv":"Hydroxykobalamin","sl":"Hidroksokobalamin","mt":"Idrossokobalamina","fr":"Hydroxocobalamine","es":"Hidroxocobalamina","ro":"Hidroxocobalamină","fi":"Hydroksokobalamiini","cs":"Hydroxokobalamin","it":"Idrossocobalamina","bg":"Хидроксокобаламин","el":"Υδροξοκοβαλαμίνη"}},"en:menaquinone":{"parents":["en:vitamin-k"],"name":{"fr":"Ménaquinone","el":"Μενακινόνη","it":"Menachinone","sk":"Menachinón","ja":"ビタミンK2","lv":"Menahinons","pt":"Menaquinona","de":"Menachinon","cs":"Menachinon","fi":"Menakinoni","ro":"Menachinonă","es":"Menaquinona","bg":"Менахинон","lt":"Menachinonas","pl":"Menachinon","mt":"Menakinona","sv":"Menakinon","sl":"Menakinon","hu":"Menakinon","en":"Menaquinone","nl":"Menachinon","et":"Menakinoon"},"synonyms":{"pt":["menaquinona"],"lv":["menahinons"],"de":["Menachinon"],"fr":["ménaquinone","Vitamine K2"],"it":["menachinone"],"el":["μενακινόνη"],"sk":["menachinón"],"ja":["ビタミンK2","ビタミンＫ２","ビタミン K2","ビタミン Ｋ２","V.K2","Ｖ．Ｋ２","V.K₂","V-K2","ＶーＫ２","V-K₂"],"hu":["menakinon"],"nl":["menachinon"],"en":["Menaquinone","Vitamin K2"],"et":["menakinoon"],"fi":["menakinoni"],"cs":["menachinon"],"es":["menaquinona"],"ro":["menachinonă"],"bg":["Менахинон"],"pl":["menachinon"],"lt":["menachinonas"],"mt":["menakinona"],"sl":["menakinon"],"sv":["Menakinon"]}},"en:potassium-l-ascorbate":{"name":{"ro":"L-ascorbat de potasiu","es":"L-ascorbato potásico","fr":"L-ascorbate de potassium","cs":"L-askorbát draselný","fi":"Kalium-L-askorbaatti","el":"L-ασκορβικό κάλιο","bg":"Калиев-L-аскорбат","it":"L-ascorbato di potassio","lt":"Kalio L-askorbatas","pl":"L-askorbinian potasu","sk":"L-askorban draselný","sl":"Kalijev-L-askorbat","sv":"Kalium-L-askorbat","mt":"L-assorbat tal-potassju","hu":"Kálium-L-aszkorbát","lv":"Kālija L-askorbāts","nl":"Kalium-L-ascorbaat","en":"Potassium-L-ascorbate","pt":"L-ascorbato de potássio","et":"Kaalium-L-askorbaat","de":"Kalium-L-ascorbat"},"synonyms":{"pt":["L-ascorbato de potássio"],"nl":["kalium-L-ascorbaat"],"en":["potassium-L-ascorbate","potassium ascorbate"],"lv":["kālija L-askorbāts"],"hu":["kálium-L-aszkorbát"],"de":["Kalium-L-ascorbat"],"et":["kaalium-L-askorbaat"],"it":["L-ascorbato di potassio"],"bg":["Калиев-L-аскорбат"],"el":["L-ασκορβικό κάλιο"],"fr":["L-ascorbate de potassium","ascorbate de potassium"],"es":["L-ascorbato potásico"],"ro":["L-ascorbat de potasiu"],"fi":["kalium-L-askorbaatti"],"cs":["L-askorbát draselný"],"sv":["kalium-L-askorbat"],"sl":["kalijev-L-askorbat"],"mt":["L-assorbat tal-potassju"],"pl":["L-askorbinian potasu"],"lt":["kalio L-askorbatas"],"sk":["L-askorban draselný"]},"parents":["en:vitamin-c"]},"en:vitamin-d":{"wikipedia":{"en":"https://en.wikipedia.org/wiki/Vitamin_D"},"name":{"sq":"Vitamina D","nb":"Vitamin D","ro":"Vitamina D","cs":"Vitamín D","tr":"D vitamini","si":"විටමින් D","pl":"Witamina D","ug":"ۋىتامىن D","ga":"Vitimín D","nl":"Vitamine D","en":"Vitamin D","ms":"Vitamin D","tt":"D витамины","hu":"D-vitamin","sh":"Vitamin D","et":"D-vitamiin","eo":"Vitamino D","ca":"Vitamina D","nn":"Vitamin D","el":"Βιταμίνη D","vi":"Vitamin D","fr":"Vitamine D","he":"ויטמין D","yi":"וויטאמין D","ja":"ビタミンD","ky":"Кальциферол","hi":"विटामिन डी","su":"Vitamin D","pt":"Vitamina D","da":"Vitamin D","hy":"Վիտամին D","ka":"ვიტამინი D","is":"D-vítamín","de":"Vitamin D","cy":"Fitamin D","bg":"Витамин D","mn":"Д витамин","es":"Vitamina D","az":"D vitamini","fa":"ویتامین د","fi":"D-vitamiini","sv":"Vitamin D","sl":"Vitamin D","mt":"Vitamina D","lt":"Vitaminas D","gl":"Vitamina D","pa":"ਵਿਟਾਮਿਨ ਡੀ","hr":"Vitamin D","id":"Vitamin D","mr":"ड-जीवनसत्त्व","ne":"भिटामिन डी","eu":"D bitamina","ar":"فيتامين دي","oc":"Vitamina D","te":"విటమిన్ డి","it":"Vitamina D","sr":"Витамин Д","ta":"உயிர்ச்சத்து டி","sk":"Vitamín D","dv":"ވިޓަމިން ޑީ","zh":"维生素D","uk":"Вітамін D","lv":"D vitamīns","tg":"Витамини D","ko":"비타민 D","ml":"ജീവകം ഡി","th":"วิตามินดี","bs":"Vitamin D","af":"Vitamien D","ru":"Витамин D"},"synonyms":{"ja":["ビタミンD","ビタミンＤ","ビタミン D","ビタミン Ｄ","V.D","Ｖ．Ｄ","V-D","ＶーＤ"],"ky":["Кальциферол"],"yi":["וויטאמין D"],"hi":["विटामिन डी"],"nn":["vitamin D","D-vitamin"],"el":["Βιταμίνη D"],"ca":["vitamina D"],"vi":["vitamin D"],"eo":["Vitamino D"],"he":["ויטמין D"],"fr":["vitamine D"],"is":["D-vítamín"],"de":["Vitamin D"],"cy":["Fitamin D"],"da":["Vitamin D"],"hy":["Վիտամին D"],"su":["Vitamin D"],"pt":["vitamina D","vitaminas D"],"ka":["ვიტამინი D"],"si":["විටමින් D"],"tr":["D vitamini"],"ga":["Vitimín D"],"ug":["ۋىتامىن D"],"pl":["Witamina D"],"nb":["vitamin D"],"sq":["Vitamina D"],"cs":["vitamín D"],"ro":["vitamina D"],"sh":["Vitamin D"],"et":["D-vitamiin"],"en":["vitamin D","D"],"nl":["vitamine D"],"ms":["Vitamin D"],"hu":["D-vitamin"],"tt":["D витамины"],"ta":["உயிர்ச்சத்து டி"],"sr":["витамин Д"],"sk":["Vitamín D"],"it":["vitamina D"],"te":["విటమిన్ డి"],"th":["วิตามินดี"],"af":["Vitamien D"],"ru":["Витамин D"],"bs":["Vitamin D"],"zh":["维生素D"],"uk":["Вітамін D"],"dv":["ވިޓަމިން ޑީ"],"lv":["D vitamīns"],"tg":["Витамини D"],"ml":["ജീവകം ഡി"],"ko":["비타민 D"],"mt":["Vitamina D"],"sv":["vitamin D"],"sl":["Vitamin D"],"pa":["ਵਿਟਾਮਿਨ ਡੀ"],"hr":["Vitamin D"],"lt":["Vitaminas D"],"gl":["Vitamina D"],"bg":["Витамин D"],"az":["D vitamini"],"fa":["ویتامین د"],"fi":["D-vitamiini"],"mn":["Д витамин"],"es":["vitamina D"],"eu":["D bitamina"],"ne":["भिटामिन डी"],"oc":["Vitamina D"],"ar":["فيتامين دي"],"id":["Vitamin D"],"mr":["ड-जीवनसत्त्व"]},"children":["da:vitamin-a-og-d","en:cholecalciferol","en:ergocalciferol"],"wikidata":{"en":"Q175621"}}}